Workbook

Sheet Consolidated
A1: MM, WM + SRM | B1: Grade | C1: Exp Level | D1: JD Ref ID | E1: JD | F1: Panel
A2: SAP SD, LE | B2: IS1 | C2: =_xlfn.IFNA(VLOOKUP(B2,Metadata!$G$1:$H$8,2,),"-") -> 0-2 yrs | D2: =_xlfn.CONCAT(A2,"_",B2) -> SAP SD, LE_IS1 | E2: Good communication and interpersonal skills. Should be able to learn quickly on the new areas / cross functional areas Experience either worked in the SAP AMS / SAP config and development track Experince in SAP SD mainly covering Understanding on Sales Process, Contract management, Pricing concepts, OTC, Partner Determination, Text Management, Pricing, Taxes, Billing, Credit Management, Back Orders, and Master Data Management (MDM). Experience in configuring Master Data, Document Types (Sales Order Types, Delivery Documents, Billing Documents, Credit and debit memo, etc.) including special order types (Third Party Processing, Consignment Processing, Inter-Company Billing and Inter-company stock transfers), Availability Check, Material Listing/Exclusion, Rebate processing, Deliveries and Post Goods Issues. Experience Required : 0-2 years of experience with 1 implementation on SAP ERP implementation experience and 1 AMS experience worked with global customers Good understanding of SAP Fiori apps Experience in SAP cross-functional areas such as FI/CO, MM/PP Good understanding of all types of order processing models, including B2B, B2C, EDI would be added advantage Experience in project cut-over, successful go-live and client handling during PGLS and alignment with AMS teams will be valued. Good knowledge in the below areas : Electronic data interchange (EDI) : EDI Mapping Integration: Materials Management(MM), Finance, Transportation Management, Management Accounting Experience of third-party application integration using SAP PI/PO such as WM etc.
A3: SAP SD, LE | B3: IS2 | C3: =_xlfn.IFNA(VLOOKUP(B3,Metadata!$G$1:$H$8,2,),"-") -> 2-5 yrs | D3: =_xlfn.CONCAT(A3,"_",B3) -> SAP SD, LE_IS2 | E3: Good communication and interpersonal skills. Should be able to learn quickly on the new areas / cross functional areas Experience either worked in the SAP AMS / SAP config and development track Experince in SAP SD mainly covering Understanding on Sales Process, Contract management, Pricing concepts, OTC, Partner Determination, Text Management, Pricing, Taxes, Billing, Credit Management, Back Orders, and Master Data Management (MDM). Experience in configuring Master Data, Document Types (Sales Order Types, Delivery Documents, Billing Documents, Credit and debit memo, etc.) including special order types (Third Party Processing, Consignment Processing, Inter-Company Billing and Inter-company stock transfers), Availability Check, Material Listing/Exclusion, Rebate processing, Deliveries and Post Goods Issues. Experience Required : 2-5 years of experience with 1 implementation on SAP ERP implementation experience and 1 AMS experience worked with global customers Good understanding of SAP Fiori apps Experience in SAP cross-functional areas such as FI/CO, MM/PP Good understanding of all types of order processing models, including B2B, B2C, EDI would be added advantage Experience in project cut-over, successful go-live and client handling during PGLS and alignment with AMS teams will be valued. Good knowledge in the below areas : Electronic data interchange (EDI) : EDI Mapping Integration: Materials Management(MM), Finance, Transportation Management, Management Accounting Experience of third-party application integration using SAP PI/PO such as WM etc.
A4: SAP SD, LE | B4: IS3 | C4: =_xlfn.IFNA(VLOOKUP(B4,Metadata!$G$1:$H$8,2,),"-") -> 5-7 yrs | D4: =_xlfn.CONCAT(A4,"_",B4) -> SAP SD, LE_IS3 | E4: Independently take up and participate in Business workshops, Design End to End solutions . Extensive experience either worked in the SAP AMS / SAP config and development track The candidate must have strong design and implementation knowledge of SAP SD mainly covering Understanding on Sales Process, Contract management, Pricing concepts, OTC, Partner Determination, Text Management, Pricing, Taxes, Billing, Credit Management, Back Orders, and Master Data Management (MDM). Strong experience in configuring Master Data, Document Types (Sales Order Types, Delivery Documents, Billing Documents, Credit and debit memo, etc.) including special order types (Third Party Processing, Consignment Processing, Inter-Company Billing and Inter-company stock transfers), Availability Check, Material Listing/Exclusion, Rebate processing, Deliveries and Post Goods Issues. Exceptional communication and interpersonal skills. Experience Required : Minimum 5-7 years of experience with 1-2 implementation on SAP ERP implementation experience and 2 AMS experience worked with global customers Good understanding of SAP Fiori apps Experience in SAP cross-functional areas such as FI/CO, MM/PP Strong understanding of all types of order processing models, including B2B, B2C, EDI. Business knowledge and solution design experience in all areas of the Order To Cash cycle, including order processing and credit management Proven experience in project cut-over, successful go-live and client handling during PGLS and alignment with AMS teams will be valued. Should also have additional knowledge in the below areas : Electronic data interchange (EDI) : EDI Mapping Integration: Materials Management(MM), Finance, Transportation Management, Management Accounting Experience of third-party application integration using SAP PI/PO such as WM etc.
A5: SAP SD, LE | B5: IS4 | C5: =_xlfn.IFNA(VLOOKUP(B5,Metadata!$G$1:$H$8,2,),"-") -> 7-10 yrs | D5: =_xlfn.CONCAT(A5,"_",B5) -> SAP SD, LE_IS4 | E5: Independently take up and participate in Business workshops, Design End to End solutions with SAP Activate, Agile and DevOps methodologies. Extensive experience either in leading the SAP AMS / leading the SAP config and development track The candidate must have strong design and implementation knowledge of SAP SD mainly covering Understanding on Sales Process, Contract management, Pricing concepts, OTC, Partner Determination, Text Management, Pricing, Taxes, Billing, Credit Management, Back Orders, and Master Data Management (MDM). Strong experience in configuring Master Data, Document Types (Sales Order Types, Delivery Documents, Billing Documents, Credit and debit memo, etc.) including special order types (Third Party Processing, Consignment Processing, Inter-Company Billing and Inter-company stock transfers), Availability Check, Material Listing/Exclusion, Rebate processing, Deliveries and Post Goods Issues. Exceptional communication and interpersonal skills. Experience Required : Minimum 7-10 years of experience with 2-3 implementation on SAP ERP implementation experience Good understanding of SAP Fiori apps Experience in SAP cross-functional areas such as FI/CO, MM/PP Strong understanding of all types of order processing models, including B2B, B2C, EDI. Business knowledge and solution design experience in all areas of the Order To Cash cycle, including order processing and credit management Proven experience in project cut-over, successful go-live and client handling during PGLS and alignment with AMS teams will be valued. Should also have additional knowledge in the below areas : Electronic data interchange (EDI) : EDI Mapping Integration: Materials Management(MM), Finance, Transportation Management, Management Accounting Experience of third-party application integration using SAP PI/PO such as WM etc.
A7: MM, WM + SRM | B7: IS1 | C7: =_xlfn.IFNA(VLOOKUP(B7,Metadata!$G$1:$H$8,2,),"-") -> 0-2 yrs | D7: =_xlfn.CONCAT(A7,"_",B7) -> MM, WM + SRM_IS1 | E7: Experience either in wored in SAP AMS / SAP config and development track Good communication and interpersonal skills. Should be able to learn quickly on the new areas / cross functional areas Should possess natural analytical way of thinking and troubleshooting issues. Technical analysis and documentation of SAP MM/WM application, and it’s integration with other SAP applications like SAP TM, SAP SD, SAP FI and 3rd party applications. Experience Required : Experienced in the areas of SAP ERP MM-PO & MM-IM including Purchase Requisition and Purchase Orders, set up of stock transport orders, Purchase Pricing, PO Release and approvals, Inventory movements and integration to SAP SD (Sales and distribution) SAP Finance, SAP WM (Warehouse Management) etc. Inbound and Outbound IDOCs and Interfaces, Purchasing Output Management and Forms. Understanding in Master data related to procurement like materials, Info records, Business Partners etc. Good understanding of SAP Fiori apps Experienced with 3rd party interfaces and integration. Experience in project cut-over, successful go-live and client handling during PGLS and alignment with AMS teams will be valued. Experience in Third party integration – Movilizer, Barcoding, 3rd party applications would be added advantage
A8: MM, WM + SRM | B8: IS2 | C8: =_xlfn.IFNA(VLOOKUP(B8,Metadata!$G$1:$H$8,2,),"-") -> 2-5 yrs | D8: =_xlfn.CONCAT(A8,"_",B8) -> MM, WM + SRM_IS2 | E8: Experience either in wored in SAP AMS / SAP config and development track Good communication and interpersonal skills. Should be able to learn quickly on the new areas / cross functional areas Should possess natural analytical way of thinking and troubleshooting issues. Technical analysis and documentation of SAP MM/WM application, and it’s integration with other SAP applications like SAP TM, SAP SD, SAP FI and 3rd party applications. Experience Required : Experienced in the areas of SAP ERP MM-PO & MM-IM including Purchase Requisition and Purchase Orders, set up of stock transport orders, Purchase Pricing, PO Release and approvals, Inventory movements and integration to SAP SD (Sales and distribution) SAP Finance, SAP WM (Warehouse Management) etc. Inbound and Outbound IDOCs and Interfaces, Purchasing Output Management and Forms. Understanding in Master data related to procurement like materials, Info records, Business Partners etc. Good understanding of SAP Fiori apps Experienced with 3rd party interfaces and integration. Experience in project cut-over, successful go-live and client handling during PGLS and alignment with AMS teams will be valued. Experience in Third party integration – Movilizer, Barcoding, 3rd party applications would be added advantage
A9: MM, WM + SRM | B9: IS3 | C9: =_xlfn.IFNA(VLOOKUP(B9,Metadata!$G$1:$H$8,2,),"-") -> 5-7 yrs | D9: =_xlfn.CONCAT(A9,"_",B9) -> MM, WM + SRM_IS3 | E9: Independently take up and participate in Business workshops, Design End to End solutions Extensive experience either in wored in SAP AMS / SAP config and development track Should possess natural analytical way of thinking and troubleshooting issues. Good communication and interpersonal skills. Technical analysis and documentation of SAP MM/WM application, and it’s integration with other SAP applications like SAP TM, SAP SD, SAP FI and 3rd party applications. Experience Required : Experienced in the areas of SAP ERP MM-PO & MM-IM including Purchase Requisition and Purchase Orders, set up of stock transport orders, Purchase Pricing, PO Release and approvals, Inventory movements and integration to SAP SD (Sales and distribution) SAP Finance, SAP WM (Warehouse Management) etc. Inbound and Outbound IDOCs and Interfaces, Purchasing Output Management and Forms. Understanding in Master data related to procurement like materials, Info records, Business Partners etc. Good understanding of SAP Fiori apps Experienced with 3rd party interfaces and integration. 5-7 years overall experience and Implementation and delivery experience, which should include at least 1-2 full project lifecycles on SAP ERP and 2 AMS support experience worked across global customers Proven experience in project cut-over, successful go-live and client handling during PGLS and alignment with AMS teams will be valued. Third party integration – Movilizer, Barcoding, 3rd party applications
A10: MM, WM + SRM | B10: IS4 | C10: =_xlfn.IFNA(VLOOKUP(B10,Metadata!$G$1:$H$8,2,),"-") -> 7-10 yrs | D10: =_xlfn.CONCAT(A10,"_",B10) -> MM, WM + SRM_IS4 | E10: Independently take up and participate in Business workshops, Design End to End solutions with SAP Activate, Agile and DevOps methodologies. Extensive experience either in leading the SAP AMS / leading the SAP config and development track Requirements gathering, project planning and management, solution design, configuration and customization of SAP ERP MM-PO and MM-IM, WM Should possess natural analytical way of thinking and troubleshooting issues. Exceptional communication and interpersonal skills. Technical analysis and documentation of SAP MM/WM application, and it’s integration with other SAP applications like SAP TM, SAP SD, SAP FI and 3rd party applications. Experience Required : Highly experienced in the areas of SAP ERP MM-PO & MM-IM including Purchase Requisition and Purchase Orders, set up of stock transport orders, Purchase Pricing, PO Release and approvals, Inventory movements and integration to SAP SD (Sales and distribution) SAP Finance, SAP WM (Warehouse Management) etc. Inbound and Outbound IDOCs and Interfaces, Purchasing Output Management and Forms. Understanding in Master data related to procurement like materials, Info records, Business Partners etc. Good understanding of SAP Fiori apps Experienced with 3rd party interfaces and integration. 7-10 years overall experience and Implementation and delivery experience, which should include at least 2-3 full project lifecycles on SAP ERP. Proven experience in project cut-over, successful go-live and client handling during PGLS and alignment with AMS teams will be valued. Third party integration – Movilizer, Barcoding, 3rd party applications
A11: MM, WM + SRM | B11: IS5 | C11: =_xlfn.IFNA(VLOOKUP(B11,Metadata!$G$1:$H$8,2,),"-") -> 10-15 yrs | D11: =_xlfn.CONCAT(A11,"_",B11) -> MM, WM + SRM_IS5 | E11: Independently take up and participate in Business workshops, Design End to End solutions with SAP Activate, Agile and DevOps methodologies. Extensive experience either in leading the SAP AMS / leading the SAP config and development track Requirements gathering, project planning and management, solution design, configuration and customization of SAP ERP MM-PO and MM-IM, WM Should possess natural analytical way of thinking and troubleshooting issues. Exceptional communication and interpersonal skills. Technical analysis and documentation of SAP MM/WM application, and it’s integration with other SAP applications like SAP TM, SAP SD, SAP FI and 3rd party applications. Experience Required : Highly experienced in the areas of SAP ERP MM-PO & MM-IM including Purchase Requisition and Purchase Orders, set up of stock transport orders, Purchase Pricing, PO Release and approvals, Inventory movements and integration to SAP SD (Sales and distribution) SAP Finance, SAP WM (Warehouse Management) etc. Inbound and Outbound IDOCs and Interfaces, Purchasing Output Management and Forms. Understanding in Master data related to procurement like materials, Info records, Business Partners etc. Good understanding of SAP Fiori apps Experienced with 3rd party interfaces and integration. 10+ years overall experience and Implementation and delivery experience, which should include at least 2-3 full project lifecycles on SAP ERP. Proven experience in project cut-over, successful go-live and client handling during PGLS and alignment with AMS teams will be valued. Third party integration – Movilizer, Barcoding, 3rd party applications
A13: FI, CO | B13: IS1 | C13: =_xlfn.IFNA(VLOOKUP(B13,Metadata!$G$1:$H$8,2,),"-") -> 0-2 yrs | D13: =_xlfn.CONCAT(A13,"_",B13) -> FI, CO_IS1 | E13: Should possess natural analytical way of thinking and troubleshooting issues. Good communication and interpersonal skills. Should be able to learn quickly on the new areas / cross functional areas Pls look for unique roles as follows : 1. SAP FICO, 2. SAP Treasury Managemant, 3. SAP Cash Management, 4. SAP Central Finance Experience Required : 0-2 years of experience with 1 implementation in SAP ERP and 1 AMS expereince worked with Global customer Experience in SAP cross-functional areas such as SD, MM/PP, PS Good knowledge in all types of order processing models, including B2B, B2C, EDI. Experience in project cut-over, successful go-live and client handling during PGLS and alignment with AMS teams will be valued. Experience in FI: G/L, AP, AR, Treasury, Assets, Closing and Reporting, CO: CCA, PCA, Internal order, CO-PA, CO-PC Experience in Controlling submodules like CO-Product Costing and CO-Profitability Analysis and CO-Profit center Accounting is must. SAP Functional configuration expertise in General Ledger (FI- GL), Controlling (CO), Accounts Receivable (AR), Accounts Payable (AP), Asset Accounting (AA), Project Systems (PS) Profitability Analysis (PA), New GL, Experience in Financial Month end Activity, Financial Closing Cockpit(Task template, Task list) and Intercompany reconciliation process. Good to have knowledge in Fiori Apps, Fiori Launchpad, Fiori Launchpad Designer configuration & feature and Fiori application types.
A14: FI, CO | B14: IS2 | C14: =_xlfn.IFNA(VLOOKUP(B14,Metadata!$G$1:$H$8,2,),"-") -> 2-5 yrs | D14: =_xlfn.CONCAT(A14,"_",B14) -> FI, CO_IS2 | E14: Should possess natural analytical way of thinking and troubleshooting issues. Good communication and interpersonal skills. Should be able to learn quickly on the new areas / cross functional areas Pls look for unique roles as follows : 1. SAP FICO, 2. SAP Treasury Managemant, 3. SAP Cash Management, 4. SAP Central Finance Experience Required : 2-5 years of experience with 1 implementation in SAP ERP and 1 AMS expereince worked with Global customer Experience in SAP cross-functional areas such as SD, MM/PP, PS Good knowledge in all types of order processing models, including B2B, B2C, EDI. Experience in project cut-over, successful go-live and client handling during PGLS and alignment with AMS teams will be valued. Experience in FI: G/L, AP, AR, Treasury, Assets, Closing and Reporting, CO: CCA, PCA, Internal order, CO-PA, CO-PC Experience in Controlling submodules like CO-Product Costing and CO-Profitability Analysis and CO-Profit center Accounting is must. SAP Functional configuration expertise in General Ledger (FI- GL), Controlling (CO), Accounts Receivable (AR), Accounts Payable (AP), Asset Accounting (AA), Project Systems (PS) Profitability Analysis (PA), New GL, Experience in Financial Month end Activity, Financial Closing Cockpit(Task template, Task list) and Intercompany reconciliation process. Good to have knowledge in Fiori Apps, Fiori Launchpad, Fiori Launchpad Designer configuration & feature and Fiori application types.
A15: FI, CO | B15: IS3 | C15: =_xlfn.IFNA(VLOOKUP(B15,Metadata!$G$1:$H$8,2,),"-") -> 5-7 yrs | D15: =_xlfn.CONCAT(A15,"_",B15) -> FI, CO_IS3 | E15: Independently take up and participate in Business workshops, Design End to End solutions with SAP Should possess natural analytical way of thinking and troubleshooting issues. Good communication and interpersonal skills. Pls look for unique roles as follows : 1. SAP FICO, 2. SAP Treasury Managemant, 3. SAP Cash Management, 4. SAP Central Finance Experience Required : Minimum 5-7 years of experience with 1-2 implementation in SAP ERP and 3 AMS expereince worked with Global customer Experience in SAP cross-functional areas such as SD, MM/PP, PS Strong understanding of all types of order processing models, including B2B, B2C, EDI. Proven experience in project cut-over, successful go-live and client handling during PGLS and alignment with AMS teams will be valued. Strong experience in FI: G/L, AP, AR, Treasury, Assets, Closing and Reporting, CO: CCA, PCA, Internal order, CO-PA, CO-PC Very good experience in Controlling submodules like CO-Product Costing and CO-Profitability Analysis and CO-Profit center Accounting is must. SAP Functional configuration expertise in General Ledger (FI- GL), Controlling (CO), Accounts Receivable (AR), Accounts Payable (AP), Asset Accounting (AA), Project Systems (PS) Profitability Analysis (PA), New GL, Experience in Financial Month end Activity, Financial Closing Cockpit(Task template, Task list) and Intercompany reconciliation process. Experience with Simple Finance / Central Finance exposure will be given preference Project experience activities to include preparation, synchronization, conversion and post processing, table mapping for HANA, comprehensive knowledge of BP roles and functionality of S4 HANA Finance is preferred. Should have an overview of Deployment option for S4H. Good to have knowledge in Fiori Apps, Fiori Launchpad, Fiori Launchpad Designer configuration & feature and Fiori application types.
... A89: PLM (MDG and ECC) | B89: IS4 | C89: =_xlfn.IFNA(VLOOKUP(B89,Metadata!$G$1:$H$8,2,),"-") -> 7-10 yrs | D89: =_xlfn.CONCAT(A89,"_",B89) -> PLM (MDG and ECC)_IS4 | E89: At least 7 years’ experience with SAP implementation and SAP services management with large global organisations with large SAP installations across multiple geographies. Have onsite delivery experience around 6+ yeaear preferably in APAC and Europe Extensive experience in delivering Agile, DevOps, Activate methology Should have Delivery management experience of 15+ years in SAP implementation, Rollout, Managed Services for manufacturing/CPG domain Lead the assessment and gap analysis of MDM projects, test and validate all releases and regression Support business users with MDG data (customer, pricing, vendor, finance and accounting, APO, HR, workflow processes) Manages the analysis and execution of new master data setup or data changes Effectively coordinate with internal team, partners and Customer's data governanace COE to manage the day-to-day maintenance requirement Automates access control the business functions can see and act upon the data in accordance with their job function Proactively seeks, analyses, adminsters and communicates actionable data to the customer around data management
A91: SAP Consultant | B91: IS6 | C91: =_xlfn.IFNA(VLOOKUP(B91,Metadata!$G$1:$H$8,2,),"-") -> 20+ yrs | D91: =_xlfn.CONCAT(A91,"_",B91) -> SAP Consultant_IS6
A93: SAP PO/PI/CPI | B93: IS1 | C93: =_xlfn.IFNA(VLOOKUP(B93,Metadata!$G$1:$H$8,2,),"-") -> 0-2 yrs | D93: =_xlfn.CONCAT(A93,"_",B93) -> SAP PO/PI/CPI_IS1 | E93: 0-2 yrs of experience in implement and deploy SAP Cloud Integration Suite solutions (CPI), SAP PO, SAP PI to achieve defined business goals Maintain skills in SAP applications process design and configuration Work as part of small teams and/or work efforts (if in an individual contributor role) to deliver integration solutions to customers. Production Support of integration processes as needed Technical configuration for domain areas Escalation point for solution design or troubleshooting with outside service partners Supporting and implementing technical integrations with a variety of global 3rd party applications. Must be a team player to collaboratively and effectively deliver high quality work product and communicate with others on multi-disciplinary teams. Responsible for troubleshooting technical problems. Map the business process to SAP Technologies-CPI, BOOMI, SAP Fiori, SAP UI5,etc.
A94: SAP PO/PI/CPI | B94: IS2 | C94: =_xlfn.IFNA(VLOOKUP(B94,Metadata!$G$1:$H$8,2,),"-") -> 2-5 yrs | D94: =_xlfn.CONCAT(A94,"_",B94) -> SAP PO/PI/CPI_IS2 | E94: 2-5 yrs of experience in Design, implement and deploy SAP Cloud Integration Suite solutions (CPI), SAP PO, SAP PI to achieve defined business goals Maintain skills in SAP applications process design and configuration SAP application design, development, integration, testing, deployment and technical architecture Work as part of small teams and/or work efforts (if in an individual contributor role) to deliver integration solutions to customers. Implement or deploy capabilities as required: End-to-End process design, testing strategy, cutover plans, training, etc. Production Support of integration processes as needed Technical configuration for domain areas Escalation point for solution design or troubleshooting with outside service partners Supporting and implementing technical integrations with a variety of global 3rd party applications. Understand end-to-end Business Processes Must be a team player to collaboratively and effectively deliver high quality work product and communicate with others on multi-disciplinary teams. Responsible for successful end to end delivery. Responsible for troubleshooting technical problems. Map the business process to SAP Technologies-CPI, BOOMI, SAP Fiori, SAP UI5,etc.
A95: SAP PO/PI/CPI | B95: IS3 | C95: =_xlfn.IFNA(VLOOKUP(B95,Metadata!$G$1:$H$8,2,),"-") -> 5-7 yrs | D95: =_xlfn.CONCAT(A95,"_",B95) -> SAP PO/PI/CPI_IS3 | E95: 5-7 yrs of experience in Design, implement and deploy SAP Cloud Integration Suite solutions (CPI), SAP PO, SAP PI to achieve defined business goals Maintain skills in SAP applications process design and configuration SAP application design, development, integration, testing, deployment and technical architecture Work as part of small teams and/or work efforts (if in an individual contributor role) to deliver integration solutions to customers. Implement or deploy capabilities as required: End-to-End process design, testing strategy, cutover plans, training, etc. Production Support of integration processes as needed Technical configuration for domain areas Escalation point for solution design or troubleshooting with outside service partners Supporting and implementing technical integrations with a variety of global 3rd party applications. Understand end-to-end Business Processes Must be a team player to collaboratively and effectively deliver high quality work product and communicate with others on multi-disciplinary teams. Responsible for successful end to end delivery. Responsible for troubleshooting technical problems. Map the business process to SAP Technologies-CPI, BOOMI, SAP Fiori, SAP UI5,etc.
A96: SAP PO/PI/CPI | B96: IS4 | C96: =_xlfn.IFNA(VLOOKUP(B96,Metadata!$G$1:$H$8,2,),"-") -> 7-10 yrs | D96: =_xlfn.CONCAT(A96,"_",B96) -> SAP PO/PI/CPI_IS4 | E96: 7+ years of experince in SAP integration including SAP PO, PI and CPI Analyze integration requirements, design and implement complex, state-of-the-art end-to-end integration scenarios across multiple technologies and multiple modules. Define integration architectures and API strategies. Interface design and implementation based on SAP Cloud Platform Integration Suite and SAP Process Orchestration. Integration of cloud solutions and platforms (SAP, Salesforce, Azure, AWS), IoT services and external business partners. Evaluate new SAP technologies and supporting building know-how in these areas, which are integrated into cbs processes. Technical integration consulting and development as part of global SAP ECC, S/4HANA or C/4HANA implementation projects. Be responsible for cbs projects and customers in the technology area as well as engage in pre-sales support in all kinds of SAP technology topics. Act as a technical team lead for the requested deliverables which includes adhering to the timeline, effort and assuring quality. Collaboration with the onsite team. Coach colleagues in functional, technical, and methodic topics. Sharing knowledge and experience with the colleagues. Contribute to cbs best practices and methodologies. Desire for a dynamic and prestigious work environment.
A97: SAP PO/PI/CPI | B97: IS5 | C97: =_xlfn.IFNA(VLOOKUP(B97,Metadata!$G$1:$H$8,2,),"-") -> 10-15 yrs | D97: =_xlfn.CONCAT(A97,"_",B97) -> SAP PO/PI/CPI_IS5 | E97: 10+ years of experince in SAP integration including SAP PO, PI and CPI Analyze integration requirements, design and implement complex, state-of-the-art end-to-end integration scenarios across multiple technologies and multiple modules. Define integration architectures and API strategies. Interface design and implementation based on SAP Cloud Platform Integration Suite and SAP Process Orchestration. Integration of cloud solutions and platforms (SAP, Salesforce, Azure, AWS), IoT services and external business partners. Evaluate new SAP technologies and supporting building know-how in these areas, which are integrated into cbs processes. Technical integration consulting and development as part of global SAP ECC, S/4HANA or C/4HANA implementation projects. Be responsible for cbs projects and customers in the technology area as well as engage in pre-sales support in all kinds of SAP technology topics. Act as a technical team lead for the requested deliverables which includes adhering to the timeline, effort and assuring quality. Collaboration with the onsite team. Coach colleagues in functional, technical, and methodic topics. Sharing knowledge and experience with the colleagues. Contribute to cbs best practices and methodologies.
A98: SAP PO/PI/CPI | B98: I5+ | C98: =_xlfn.IFNA(VLOOKUP(B98,Metadata!$G$1:$H$8,2,),"-") -> 15 - 20 yrs | D98: =_xlfn.CONCAT(A98,"_",B98) -> SAP PO/PI/CPI_I5+ | E98: 15+ years of experince in SAP integration including SAP PO, PI and CPI Analyze integration requirements, design and implement complex, state-of-the-art end-to-end integration scenarios across multiple technologies and multiple modules. Define integration architectures and API strategies. Interface design and implementation based on SAP Cloud Platform Integration Suite and SAP Process Orchestration. Integration of cloud solutions and platforms (SAP, Salesforce, Azure, AWS), IoT services and external business partners. Evaluate new SAP technologies and supporting building know-how in these areas, which are integrated into cbs processes. Technical integration consulting and development as part of global SAP ECC, S/4HANA or C/4HANA implementation projects. Be responsible for cbs projects and customers in the technology area as well as engage in pre-sales support in all kinds of SAP technology topics. Act as a technical team lead for the requested deliverables which includes adhering to the timeline, effort and assuring quality. Collaboration with the onsite team. Coach colleagues in functional, technical, and methodic topics. Sharing knowledge and experience with the colleagues. Contribute to cbs best practices and methodologies.
A100: Mulesoft | B100: IS1 | C100: =_xlfn.IFNA(VLOOKUP(B100,Metadata!$G$1:$H$8,2,),"-") -> 0-2 yrs | D100: =_xlfn.CONCAT(A100,"_",B100) -> Mulesoft_IS1 | E100: Required Skills: Responsible for building integration solutions on the MuleSoft Anypoint Platform with design of specifications, design and development of APIs meeting, deployment, testing and Support. 0- 2 yrs of Experience required in Mulesoft Development. Experience working directly with technical and business teams. Knowledge of SDLC, IT governance and operations. Experience in packaging and deploying MuleSoft applications. Experience working with CI/CD tools like GitHub, Maven, Azure DevOps etc. Experience with messaging platforms Anypoint MQ,IBM MQ etc. Experience working with Mule Connectors ( Standard & Custom). Bachelors degree required. Good verbal and written communication skills are essential. Strong critical thinking and problem-solving skills. Experience working with overseas teams.
A101: Mulesoft | B101: IS2 | C101: =_xlfn.IFNA(VLOOKUP(B101,Metadata!$G$1:$H$8,2,),"-") -> 2-5 yrs | D101: =_xlfn.CONCAT(A101,"_",B101) -> Mulesoft_IS2 | E101: Required Skills: Responsible for building integration solutions on the MuleSoft Anypoint Platform with design of specifications, design and development of APIs meeting, deployment, testing and Support. 2- 5 yrs of Experience required in Mulesoft Development. Experience working directly with technical and business teams. Knowledge of SDLC, IT governance and operations. Experience in packaging and deploying MuleSoft applications. Experience working with CI/CD tools like GitHub, Maven, Azure DevOps etc. Experience with messaging platforms Anypoint MQ,IBM MQ etc. Experience working with Mule Connectors ( Standard & Custom). Bachelors degree required. Good verbal and written communication skills are essential. Strong critical thinking and problem-solving skills. Experience working with overseas teams. MuleSoft developer certified shall be preferred
A102: Mulesoft | B102: IS3 | C102: =_xlfn.IFNA(VLOOKUP(B102,Metadata!$G$1:$H$8,2,),"-") -> 5-7 yrs | D102: =_xlfn.CONCAT(A102,"_",B102) -> Mulesoft_IS3 | E102: 5+ years of software development experience with extensive integration experience in MuleSoft 4+ years of development experience using MuleSoft suite of products - Any point Platform, Design Center, Connectors, Exchange, Runtime manager and API Management tools. 2+ years of application development experience. Strong technical knowledge and work experience in implementing integrations with Web services / SOAP / RESTful/gRPC/ Graphql / file based integration patterns and use of different Mule connectors (Any point MQ, Kafka, Azure Event Hub, File, Http/Https, Siebel, ServiceNow, SAP SuccessFactors, Salesforce, Oracle EBS Connector etc.) Experience in developing Microservices architecture-based API, Event Driven and Batch style integration patterns Experience in Java 1.8, Data Weave, JSON, Open API and RAML is required in a cloud or hybrid architecture platfor Business process knowledge and work experience with ERP / Cloud systems within Sales, Marketing, Finance and CRM domains. Experience with DevOps culture and CI/CD tools Participate in proof-of-concept to demonstrate feasibility. Experience of security models, encryption, routing, transformations, error handling, logging, and testing frameworks. Working experience on Agile, Azure Devops and SDLC processes. Good communication, analytical skills.
A103: Mulesoft | B103: IS4 | C103: =_xlfn.IFNA(VLOOKUP(B103,Metadata!$G$1:$H$8,2,),"-") -> 7-10 yrs | D103: =_xlfn.CONCAT(A103,"_",B103) -> Mulesoft_IS4 | E103: 7+ years of Overall experience and Experience in architecture, design and implementation of MuleSoft integration and integration experience along with Java based solutions (refer mandatory skills) Candidate should have 4+ years of Architecture design and consulting skills Extensive experience in API's / Web services / SOA development Extensive experience with successful implementations of highly scalable and highly available systems Experience with agile/DevOps development processes Skills Required Expertise in Mulesoft, Expertise in Java, Web services, APIs, SOA and any RDBMS Messaging - JMS APIs, ActiveMQ etc Development tools (Maven, Ant, Jira, Eclipse) Any source versioning control tools expertise Good knowledge on OOPS concepts and design/integration patterns
A104: Mulesoft | B104: IS5 | C104: =_xlfn.IFNA(VLOOKUP(B104,Metadata!$G$1:$H$8,2,),"-") -> 10-15 yrs | D104: =_xlfn.CONCAT(A104,"_",B104) -> Mulesoft_IS5 | E104: 10+ years of experience as an Architect for developing API, ESB, Middleware tools based messaging or EDI or customer integration. Application developed involves communication with both .Net, Java, or Microservices based new or existing legacy platforms Excellent knowledge and hands-on experience with multiple platforms and related technologies: MuleSoft, any Opensource ESB, .Net WebAPI, Java Messaging Service, Apache Kafka, IBM CP4I, Rabbit MQ. Experience with common architectures like Hub-Spoke, Federated ESB, Open API, Queues, Streaming Architecture Knowledge of common software engineering practices Requirements Engineering, Design Patterns, Code Analysis, Performance, DevOps (CI/CD) and architecture modelling practices (UML, Swagger, etc.) Architect the solution for web and hybrid enterprise applications for several platforms (Mobile, Web, B2C/ B2B, Data systems) Know the best practices and risks in terms of security. Always keen to learn new things, share your knowledge, embrace change and learn from past experiences. Integrate with other application developed in Cloud or on-premise Collaborate with Product Team and Application team Review code for well-designed components and testable code Integrate software components into a fully functional software system Troubleshoot, debug and upgrade existing integration Comply with project plans Comply to industry best practices and standards Should possess excellent time management skills
A106: Talend | B106: IS1 | C106: =_xlfn.IFNA(VLOOKUP(B106,Metadata!$G$1:$H$8,2,),"-") -> 0-2 yrs | D106: =_xlfn.CONCAT(A106,"_",B106) -> Talend_IS1 | E106: 0-2 yrs of Talend developer experience , ETL development , RDBMS , SQL , TAC, TMC. • Knowledge and hands-on experience with ETL development • Hands on experience on implementing different loading strategies like SCD1 and SCD2, Table/ partition refresh, insert update, Swap Patriation using Talend. • Experience in Consuming and writing data from and to Flat files, RDMBS systems, MPPS, Jason and XML using Talend • Experience on RDBMS systems and concepts • Expertise in writing and complex SQL queries and developing Database components including creating views, stored procedures, triggers etc. • Create test cases and perform unit testing of ETL Jobs using Talend. • Hands on experience on ETL jobs orchestration using Talend. • Hands on experience on creating Triggers on TAC server for Scheduling the Talend jobs • Experience on creating batch level processing, parallel process using Talend. • Analytical mind with a problem-solving and debugging skills. • Excellent Communication Skills • Awareness of Replication, Synchronization and Disaster Management techniques • Awareness of Data Quality Management
... A160: Integration Service Delivery Manager | B160: IS5 | C160: =_xlfn.IFNA(VLOOKUP(B160,Metadata!$G$1:$H$8,2,),"-") -> 10-15 yrs | D160: =_xlfn.CONCAT(A160,"_",B160) -> Integration Service Delivery Manager_IS5 | E160: 10+ years of experince in SAP integration including SAP PO, PI and CPI Analyze integration requirements, design and implement complex, state-of-the-art end-to-end integration scenarios across multiple technologies and multiple modules. Define integration architectures and API strategies. Interface design and implementation based on SAP Cloud Platform Integration Suite and SAP Process Orchestration. Integration of cloud solutions and platforms (SAP, Salesforce, Azure, AWS), IoT services and external business partners. Evaluate new SAP technologies and supporting building know-how in these areas, which are integrated into cbs processes. Technical integration consulting and development as part of global SAP ECC, S/4HANA or C/4HANA implementation projects. Be responsible for cbs projects and customers in the technology area as well as engage in pre-sales support in all kinds of SAP technology topics. Act as a technical team lead for the requested deliverables which includes adhering to the timeline, effort and assuring quality. Collaboration with the onsite team. Coach colleagues in functional, technical, and methodic topics. Sharing knowledge and experience with the colleagues. Contribute to cbs best practices and methodologies.
A161: Cloud DM-Onsite/KL | B161: IS5 | C161: 12-20 years | D161: =_xlfn.CONCAT(A161,"_",B161) -> Cloud DM-Onsite/KL_IS5 | E161: Service Delivery Manager-Cloud Services ITC is looking for the Program Manager/Service Delivery Manager to manage a portfolio of customer migration assessments/Managed services for Cloud platforms with 12-20 years of experience across a range of levels from different backgrounds and with various skills and expertise. In this role who can work with Customers, Delivery team, and Cloud Partners to deliver data-backed assessments to customers for migrating their current on-premises workloads to the Cloud. We are seeking the one who can demonstrate the below skills or those who are keen to gain them: Certifications Any competitive Cloud Practitioner or Associate Solution Architecture Certification Professional certification on Project/Program Management is highly desirable Azure or AWS Administration or Architect level certification would be added advantage Roles and Responsibilities Program Manager should have good experience in managing large AWS/Azure implementation migration programs and running managed service delivery. The Program Manager serves a key upfront role on these assessments by ensuring that customers are choosing the correct tools and programs throughout the planning and execution of their migration, as well as serving as a contact person to reduce friction and roadblocks throughout the customer’s migration journey and running efficient service delivery. Gather requirements from customers regarding desired outcomes of the assessment to ensure the appropriate tools and teams are included. Ensure that an assessment is running smoothly and on time, following up to offer extra assistance when required. Dealing with stakeholders, plan, organize, schedule, control, and monitor projects to ensure timely completion, cost effectiveness, and customer satisfaction. Proactively identifies potential delivery issues and drives resolution to avoid customer impact. Always look for area of opportunity for automation adoption and optimize resource efforts, efficiency and drive ROI Identifies scope changes from the original plan or agreement and escalates to the management team. Setting up the team and mentoring them Works directly with technical team and ensure project success and managing the team. Develop, maintain, and manage relationships with client executives and engagement sponsors and provides complex metrics and reporting support to all relevant stakeholders. Knowledge working closely with ServiceNow/Jira or any other project management software. Excellent oral and written communications skills as necessary to communicate, negotiate, advice, or resolve issues that are highly complex including the ability to communicate technical information to nontechnical users effectively. Manage the intake process for all new Migration assessments. Position and propose the inclusion of partners for an assessment, when applicable. Provide high-level demonstrations & overviews of migration tools to outline options to internal and external customers. Provide a single point of escalation for teams needing Migration assistance, or for high profile assessments. Should be well versed with building confidence, trust and grabbing more business opportunities
A162: Azure Architect-Onsite/KL | B162: IS5 | C162: 10-15 Years | D162: =_xlfn.CONCAT(A162,"_",B162) -> Azure Architect-Onsite/KL_IS5 | E162: ITC is looking for Cloud Solution Architects with 10-15 years of experience across a range of levels from different backgrounds and with various skills and expertise. Understanding that there are many paths to acquiring the skills needed to be a successful Cloud Solution Architect, we are seeking the one who can demonstrate the below skills or those who are keen to gain them: Certifications Azure Certified Solutions Architect Associate Azure Certified Solutions Architect Professional Roles and Responsibilities Participate in technical discussion, provide consultative services to customer, guide the team based on requirements for delivery, Provide Azure technical design and thought leadership. Must have experience with designing and deploying solutions in Azure at enterprise scale, with good automation skills, Understand the customers business & application requirements and translate them into system / technical requirements. Experience with private public cloud architectures, pros/cons, and migration considerations, implementation features (OS, multi-tenancy, virtualization, orchestration, elastic scalability Extensive hands-on experience implementing infra migration, data migration and data processing using Azure services: Networking, Windows/Linux virtual machines, Container, Storage, ELB, Autoscaling, Azure Functions, Serverless Architecture, ARM Templates, Azure SQL DB/DW, Data Factory, Azure Stream Analytics, Azure Analysis Service - Must have experience in Azure IaaS and Azure active directory Proven experience assessing client’s workloads and technology landscape for Cloud suitability, develop business case and Cloud adoption roadmap Experience in working RFP's Proposals, Solutions, defining new architectures and ability to drive project from architecture standpoint Knowledge of best practices and market trends pertaining to Cloud and overall industry to provide thought leadership (seminars, whitepapers etc.,) and mentor team to build necessary competency. Ability to quickly establish credibility and trustworthiness with key stakeholders in client organization. Well versed with third party DevOps such as Jenkins, Bitbucket, docker repository, terraform, and ansible, Azure Security policy, Azure DevOps, AKS, Azure WAF, networking and ingress controller, good knowledge of working with Kafka, Datadog is added advantage Ensure success in designing, building, and migrating applications, software, and services on the Azure platform. end-to-end architecture, networking, provisioning, and management Educate customers on best practices to ensure their solutions are designed for successful deployment in the cloud. Demonstrate leadership ability to back decisions with research and the "why," and articulate several options, the pros and cons for each, and a recommendation. Understand the data requirements, source data landscape of the project and architect the solution with required solution components. Hands-on experience in designing cost-efficient, fault-tolerant, and scalable distributed systems on Azure. Understand the data processing requirements like batch computing, stream computing needs and design the solution on Azure stack
A163: AWS Architect-Onsite/Mexico | B163: IS4 | C163: 10-15 Years | D163: =_xlfn.CONCAT(A163,"_",B163) -> AWS Architect-Onsite/Mexico_IS4 | E163: TC Infotech is looking for 10-15 years of experienced and highly motivated architects who possess technical depth and strong interpersonal skills. As an AWS solution architect, you will lead technical workshops, advise customers on architectural and strategic IT decisions and design highly scalable, flexible and resilient cloud architectures that address customer business challenges. As a trusted customer advocate, the solutions architect will help organizations understand best practices around advanced AWS cloud-based solutions. Certification requirements: AWS Certified Solutions Architect Associate AWS Certified Solutions Architect Professional Roles and Responsibilities Understand technical, business & application requirements from client discussions, RFP's and Translate them into system / technical requirements and build Proposals, Solutions, Cloud suitability, develop business case and Cloud adoption roadmap Good Exp in driving and running cloud managed services for larger workloads with multi cloud platforms & Multi vendor involvment and driving cloud optimization and efficiency Lead technical workshops and advise customers on architectural and strategic IT decisions, end-to-end architecture, networking, provisioning, and management Develop AWS technical design, thought leadership, architecture blueprints and detailed documentation. Create bill of materials, including required Cloud Services (such as EC2, S3 etc.) and tools. Proven knowledge of AWS platform and tools Design, Setup and oversee the overall AWS Virtual Private Cloud VPC environment including server instance, storage instances, subnets, availability zones, network architecture and HA / DR strategies etc. Ensure success in designing, building and migrating applications, software, and services on the AWS platform. Define Migration strategy to move application to cloud Educate customers on best practices to ensure their solutions are designed for successful deployment in the cloud. Demonstrate knowledge of cloud architecture and implementation features (OS, multi-tenancy, virtualization, orchestration, elastic scalability) Demonstrate leadership ability to back decisions with research and the "why," and articulate several options, the pros and cons for each, and a recommendation. Hands-on experience in designing cost-efficient, fault-tolerant and scalable distributed systems on AWS. Understand the data processing requirements like batch computing, stream computing needs and design the solution on AWS stack. Experience in defining new architectures and ability to drive project from architecture standpoint, continuously focus on project delivery excellence and customer satisfaction Knowledge of best practices and market trends pertaining to Cloud and overall industry to provide thought leadership (seminars, whitepapers etc.,) and mentor team to build necessary competency. Ability to quickly establish credibility and trustworthiness with key stakeholders in client organization. Finalizing and preparing the templates of design documents, data flows, mapping documents, implementation, and maintenance plans. Set up process, services and tools around the cloud. Produce design documents for effectively hand over infrastructure architectures to Operations teams for successful systems engineering and implementation.
A164: Azure SME/Technical Lead | B164: IS4 | C164: 6-12 Years | D164: =_xlfn.CONCAT(A164,"_",B164) -> Azure SME/Technical Lead _IS4 | E164: Azure SME/Technical Lead ITC is looking for Cloud SME/Technical Lead with 6-12 years of experience across a range of levels from different backgrounds and with various skills and expertise. Understanding that there are many paths to acquiring the skills needed to be a successful Cloud Architect, we are seeking the one who can demonstrate the below skills or those who are keen to gain them: Certifications: - Microsoft Azure AZ-104 required Microsoft AZ-305 is a plus Other Clouds like AWS and VMWare exp would be good to have Roles and Responsibilities: - At least 6 -12 years of experience with troubleshooting, managing and monitoring Azure workloads and services Good knowledge of Azure IaaS (VMs, VNET, NSG Rules, VPN Gateways and Express Route). Creating, deploying, configuring and scaling applications on Windows/Linux Azure PaaS Experience with Azure Policy development via ARM or Terraform. Extensive hands-on experience implementing infra migration, data migration and data processing using Azure services: Networking, Windows/Linux virtual machines, Container, Storage, LB, Autoscaling, Azure Functions, Serverless Architecture, ARM Templates, Azure SQL DB/DW, Data Factory, Azure Stream Analytics, Azure Analysis Proven experience within client facing roles with ability to work creatively in a problem-solving environment Hands on experience on Azure App Service Model (Web Apps, Mobile Apps, API Apps and Web Jobs). Hands on experience on Azure storage services like SQL DB, Tables, Files, Blobs and Azure API Management Service. Experience on cloud automation, Infrastructure as Code, ARM and Terraform. Good understanding of windows server (2008/12/16) administration, DNS, DHCP and User profiles Good to have Experience of executing cloud native projects in Azure with DevOps using VSTS along with Microsoft as well as Open-Source Tools. Good understanding on MS CAF and well architected framework Good to have Azure virtual Desktop or VDI exp. Hands on experience on Azure Integration services like Service Bus and Event Hubs. Must have experience with designing and deploying solutions in Azure at enterprise scale, with good automation skills, Understand the customers business & application requirements and translate them into system / technical requirements. Experience with private public cloud architectures, pros/cons, and migration considerations, implementation features (OS, multi-tenancy, virtualization, orchestration, elastic scalability Ability to quickly establish credibility and trustworthiness with key stakeholders in client organization. Hands-on experience in designing cost-efficient, fault-tolerant, and scalable distributed systems on Azure.
A165: Azure SME/Technical Lead | B165: IS4 | C165: 6-12 Years | D165: =_xlfn.CONCAT(A165,"_",B165) -> Azure SME/Technical Lead _IS4 | E165: Azure SME/Technical Lead ITC is looking for Cloud SME/Technical Lead with 6-12 years of experience across a range of levels from different backgrounds and with various skills and expertise. Understanding that there are many paths to acquiring the skills needed to be a successful Cloud Architect, we are seeking the one who can demonstrate the below skills or those who are keen to gain them: Certifications: - Microsoft Azure AZ-104 required Microsoft AZ-305 is a plus Other Clouds like AWS and VMWare exp would be good to have Roles and Responsibilities: - At least 6 -12 years of experience with troubleshooting, managing and monitoring Azure workloads and services Good knowledge of Azure IaaS (VMs, VNET, NSG Rules, VPN Gateways and Express Route). Creating, deploying, configuring and scaling applications on Windows/Linux Azure PaaS Experience with Azure Policy development via ARM or Terraform. Extensive hands-on experience implementing infra migration, data migration and data processing using Azure services: Networking, Windows/Linux virtual machines, Container, Storage, LB, Autoscaling, Azure Functions, Serverless Architecture, ARM Templates, Azure SQL DB/DW, Data Factory, Azure Stream Analytics, Azure Analysis Proven experience within client facing roles with ability to work creatively in a problem-solving environment Hands on experience on Azure App Service Model (Web Apps, Mobile Apps, API Apps and Web Jobs). Hands on experience on Azure storage services like SQL DB, Tables, Files, Blobs and Azure API Management Service. Experience on cloud automation, Infrastructure as Code, ARM and Terraform. Good understanding of windows server (2008/12/16) administration, DNS, DHCP and User profiles Good to have Experience of executing cloud native projects in Azure with DevOps using VSTS along with Microsoft as well as Open-Source Tools. Good understanding on MS CAF and well architected framework Good to have Azure virtual Desktop or VDI exp. Hands on experience on Azure Integration services like Service Bus and Event Hubs. Must have experience with designing and deploying solutions in Azure at enterprise scale, with good automation skills, Understand the customers business & application requirements and translate them into system / technical requirements. Experience with private public cloud architectures, pros/cons, and migration considerations, implementation features (OS, multi-tenancy, virtualization, orchestration, elastic scalability Ability to quickly establish credibility and trustworthiness with key stakeholders in client organization. Hands-on experience in designing cost-efficient, fault-tolerant, and scalable distributed systems on Azure.
A166: AWS SME | B166: IS4 | C166: 6-12 Years | D166: =_xlfn.CONCAT(A166,"_",B166) -> AWS SME_IS4 | E166: AWS SME / Consultant ITC Infotech is looking for AWS consultant with 6-10 years of experience in implementing cloud platforms as per solution. You will work with clients to understand the requirements and provide required support to AWS cloud platform and suggest required changes as per industry standard and implement improvements in the client environments and provide support. If you thrive in a dynamic, collaborative workplace, ITC provides an environment where you will be challenged and inspired every single day. And if you relish the freedom to bring creative, thoughtful solutions to the table, there’s no limit to what you can accomplish here. Certifications: AWS Certified Solutions Architect Associate. Roles and Responsibilities Experience with architecting, designing, and implementing AWS/Multi-cloud services Strong architecture & design experience of Deploying Enterprise applications on AWS, monitoring and performance tuning of deployed applications on AWS Expertise in developing competencies and references through proofs-of-concept Expertise in running managed services for large customers with multi cloud/vendor platforms, Infra capacity sizing, costing of AWS services to drive optimized solution architecture, leading to optimal infra investment vs performance and scale Expertise in articulating architectural choices within various AWS services and solution methodologies In-depth knowledge of AWS components like S3, EC2, VPC/Networking, Redshift, RDS, EMR, No SQL databases, DynamoDB Study existing technology landscape and understand current application workloads Understand and document technical requirements from clients, exp in building solutions & RFP's Develop AWS technical design, thought leadership, architecture blueprints and detailed documentation. Create bill of materials, including required Cloud Services (such as EC2, S3 etc.) and tools. Proven knowledge of AWS platform and tools Design, Setup and oversee the overall AWS Virtual Private Cloud VPC environment including server instance, storage instances, subnets, availability zones, network architecture including VPN connectivity between regions and subnets and HA / DR strategies etc. Define Migration strategy to move application to cloud Set up process, services and tools around cloud, execute migration plan Leverage appropriate AWS services Validate the environment to meets all security and compliance control Should have extremely good business acumen and growth mindset
A167: Cloud Monitoring Team | B167: IS1 | C167: 1-3 years | D167: =_xlfn.CONCAT(A167,"_",B167) -> Cloud Monitoring Team_IS1 | E167: Minimum of 1+ years of relevant experience in Azure or AWS cloud monitoring,responsible for monitoring & administering various Cloud platform. Good experience in working with Azure or AWS server, patching tools, troubleshooting as well as configuration. Work in collaboration with IT Management to ensure operational security, maintenance and governance being followed. Responsibilities Responsible for working in a mixed Windows and Linux Cloud & S/W environment. Minimum of 1+ years of relevant experience in enterprise level cloud Subcription/account monitoring, administration, troubleshooting issues and P1&P2 incident management. Ready to adopt new technologies and flexible to work in 24*7 shift. Must have fair technical knowledge of virtual machines IaaS (understanding Code (PaaS) and Software as a Service (SaaS). fair in Azure Iaas and PaaS technologies and services Installed, Configured, troubleshooting of Azure Compute instances, Azure Backup, Azure Site Recovery, Azure Storage Monitor, Snapshot, Azure Storage, VNet, Load Balancers and RBAC and Azure Active directory knowledge Good knowledge and experience in Azure/AWS monitoring, Log Analytics monitoring alerts and taking them to resolution. work with next level for any Implemention, deploy and configure Azure/AWS VMs, Storage, Network & Connectivity and NSGs/ASG’s good understanding of ITSM tools like ServiceNow, service management, incident, SR, CR etc. with proactivly monitoring queue and take appropriate action as needed good communication and situation/propblem handeling things
A168: Cloud (Azure & AWS) Admin | B168: IS2 | C168: 3-5 years | D168: =_xlfn.CONCAT(A168,"_",B168) -> Cloud (Azure & AWS) Admin_IS2 | E168: Minimum of 3+ years of relevant experience in Azure other cloud Technical Specialist responsible for managing & administering various Cloud based computing solutions. Good experience in working with Azure, server, patching tools, troubleshooting as well as configuration. Work in collaboration with IT Management to ensure operational security, maintenance and governance. Responsibilities Responsible for working in a mixed Windows and Linux Cloud & S/W environment. Minimum of 3+ years of relevant experience in enterprise level cloud account administration, troubleshooting issues and P1&P2 incident management. Ready to adopt new technologies and flexible to work in 24*7 shift. Must have strong technical knowledge of virtual machines IaaS (understanding Code (PaaS) and Software as a Service (SaaS). Proficiency in Azure Iaas and PaaS technologies and services Installed, Configured, troubleshooting of Azure Compute instances, Azure Backup, Azure Site Recovery, Azure Storage Monitor, Snapshot, Azure Storage, VNet, Load Balancers and RBAC and Azure Active directory knowledge Good knowledge and experience in Azure* AWS, Monitoring, OMS, Log Analytics monitoring alerts and taking them to resolution. Implement, deploy and configure Azure & AWS VMs, Storage, Network & Connectivity and NSGs/ASG’s Manage hosting plans for Azure& AWS Infrastructure with good understanding of on premises to cloud connectivity through express route, P2S and site to site. Good in deploying managing/troubleshooting Application Gateway, load balancer issue with external firewall knowledge like Palo Alto and Barracuda Good in implementing & deploying workloads on Azure virtual machines (VMs), Azure Data Factory, Azure data bricks and APIM Implement storage related to blobs, Azure files, SQL & recovery services and managing the storage access Good to have exp in windows PowerShell scripting and Azure automation Build VMs in Azure using Azure 7 AWS Portal or any other methods
A169: Azure SME | B169: IS3 | C169: 4-8 years | D169: =_xlfn.CONCAT(A169,"_",B169) -> Azure SME_IS3 | E169: Minimum of 4+ years of relevant experience in Azure other cloud Technical Specialist responsible for managing & administering various Cloud based computing solutions. Good experience in working with Azure, server, patching tools, troubleshooting as well as configuration. Work in collaboration with IT Management to ensure operational security, maintenance and governance. Responsibilities Responsible for working in a mixed Windows and Linux Cloud & S/W environment. Minimum of 4+ years of relevant experience in enterprise level cloud account administration, troubleshooting issues and P1&P2 incident management. Ready to adopt new technologies and flexible to work in 24*7 shift. Must have strong technical knowledge of virtual machines IaaS (understanding Code (PaaS) and Software as a Service (SaaS). Proficiency in Azure Iaas and PaaS technologies and services Installed, Configured, troubleshooting of Azure Compute instances, Azure Backup, Azure Site Recovery, Azure Storage Monitor, Snapshot, Azure Storage, VNet, Load Balancers and RBAC and Azure Active directory knowledge Good knowledge and experience in Azure OMS, Log Analytics monitoring alerts and taking them to resolution. Implement, deploy and configure Azure VMs, Storage, Network & Connectivity and NSGs/ASG’s Manage hosting plans for Azure Infrastructure with good understanding of on premises to cloud connectivity through express route, P2S and site to site. Excellent in deploying managing/troubleshooting Application Gateway, load balancer issue with external firewall knowledge like Palo Alto and Barracuda Excellent in implementing & deploying workloads on Azure virtual machines (VMs), Azure Data Factory, Azure data bricks and APIM Implement storage related to blobs, Azure files, SQL & recovery services and managing the storage access Good knowledge in windows PowerShell scripting and Azure automation Build VMs in Azure using Azure Resource Manager (ARM) Templates EMS/OMS experience would be added advantage Work directly with customers to create complete solution and resolve complex support incidents related the Azure billing platform and subscription management through various support offerings. Practical problem solving and trouble shooting skills.
A170: Azure Admin | B170: IS3 | C170: 4-8 years | D170: =_xlfn.CONCAT(A170,"_",B170) -> Azure Admin_IS3 | E170: Minimum of 4+ years of relevant experience in Azure other cloud Technical Specialist responsible for managing & administering various Cloud based computing solutions. Good experience in working with Azure, server, patching tools, troubleshooting as well as configuration. Work in collaboration with IT Management to ensure operational security, maintenance and governance. Responsibilities Responsible for working in a mixed Windows and Linux Cloud & S/W environment. Minimum of 4+ years of relevant experience in enterprise level cloud account administration, troubleshooting issues and P1&P2 incident management. Ready to adopt new technologies and flexible to work in 24*7 shift. Must have strong technical knowledge of virtual machines IaaS (understanding Code (PaaS) and Software as a Service (SaaS). Proficiency in Azure Iaas and PaaS technologies and services Installed, Configured, troubleshooting of Azure Compute instances, Azure Backup, Azure Site Recovery, Azure Storage Monitor, Snapshot, Azure Storage, VNet, Load Balancers and RBAC and Azure Active directory knowledge Good knowledge and experience in Azure OMS, Log Analytics monitoring alerts and taking them to resolution. Implement, deploy and configure Azure VMs, Storage, Network & Connectivity and NSGs/ASG’s Manage hosting plans for Azure Infrastructure with good understanding of on premises to cloud connectivity through express route, P2S and site to site. Excellent in deploying managing/troubleshooting Application Gateway, load balancer issue with external firewall knowledge like Palo Alto and Barracuda Excellent in implementing & deploying workloads on Azure virtual machines (VMs), Azure Data Factory, Azure data bricks and APIM Implement storage related to blobs, Azure files, SQL & recovery services and managing the storage access Good knowledge in windows PowerShell scripting and Azure automation Build VMs in Azure using Azure Resource Manager (ARM) Templates EMS/OMS experience would be added advantage Work directly with customers to create complete solution and resolve complex support incidents related the Azure billing platform and subscription management through various support offerings. Practical problem solving and trouble shooting skills.
A171: DevOps & Automation SME | B171: IS3 | C171: 6-12 Years | D171: =_xlfn.CONCAT(A171,"_",B171) -> DevOps & Automation SME_IS3 | E171: Azure DevOps & Automation – IaC - Terraform Engineer ITC is looking for 6-10 years’ experience Azure DevOps, Automation IaC engineer with various skills and expertise such as design, develop, document, test, and debug new and existing configuration management (Terraform/Biceps) infrastructure as code. Experience with Jenkins, Terraform and GIT as source control. Provide top level support to the dev/ops team and integrate with existing infrastructure. Certification: Terraform Associate Certification and Azure DevOps Expert Roles & Responsibilities Infrastructure as Code (IaC) Engineer will provide design and engineering expertise to project team and its members to plan, analyze, design, test, and deploy infrastructure expressed as code. Well versed with Azure DevOps, Pipelines/release/ Build/deployment with complete Azure DevOps Governance controls and management Work alongside team to develop robust, secure and end-to-end designs for business solutions. Lead and/or participate in designing, developing and testing IaC solutions for IaaS and PaaS solutions for on-prem, Public and Private Cloud platforms Well versed with Terraform, Ansible, Jenkins or any other IaC and DevOps tools and Technologies. Well versed with Public Cloud Technologies and heavy automation domain knowledge and is experience with systems like Terraform, Vault, Ansible, and Kubernetes. Support IAC operations and integrating IaC with Dev-Ops pipeline Provide consultations to ensure that technical and operational requirements are achievable and being satisfied with the proposed technologies. Identify and automate process and procedures for on premise and cloud solutions (VMware, Azure, AWS) Contribute towards network/system security, risk, and operational impact Monitoring progress of the project and ensuring that it is completed on time Advising and suggesting future IT developments/trends to managers and/or clients. Remain current on IT trends pertaining to their area of practice (e.g., Agile, DevOps, Cloud, Microservices, containers) Preparing documentation for the Project and for the Business users (using standard/non-standard templates) that includes but not limited to Installation, Configuration Guides, Design solutions, Process document for Operational support, Architecture diagrams and SOPs
A172: DevOps & Automation SME | B172: IS4 | C172: 6-12 Years | D172: =_xlfn.CONCAT(A172,"_",B172) -> DevOps & Automation SME_IS4 | E172: Azure DevOps & Automation – IaC - Terraform Engineer ITC is looking for 6-10 years’ experience Azure DevOps, Automation IaC engineer with various skills and expertise such as design, develop, document, test, and debug new and existing configuration management (Terraform/Biceps) infrastructure as code. Experience with Jenkins, Terraform and GIT as source control. Provide top level support to the dev/ops team and integrate with existing infrastructure. Certification: Terraform Associate Certification and Azure DevOps Expert Roles & Responsibilities Infrastructure as Code (IaC) Engineer will provide design and engineering expertise to project team and its members to plan, analyze, design, test, and deploy infrastructure expressed as code. Well versed with Azure DevOps, Pipelines/release/ Build/deployment with complete Azure DevOps Governance controls and management Work alongside team to develop robust, secure and end-to-end designs for business solutions. Lead and/or participate in designing, developing and testing IaC solutions for IaaS and PaaS solutions for on-prem, Public and Private Cloud platforms Well versed with Terraform, Ansible, Jenkins or any other IaC and DevOps tools and Technologies. Well versed with Public Cloud Technologies and heavy automation domain knowledge and is experience with systems like Terraform, Vault, Ansible, and Kubernetes. Support IAC operations and integrating IaC with Dev-Ops pipeline Provide consultations to ensure that technical and operational requirements are achievable and being satisfied with the proposed technologies. Identify and automate process and procedures for on premise and cloud solutions (VMware, Azure, AWS) Contribute towards network/system security, risk, and operational impact Monitoring progress of the project and ensuring that it is completed on time Advising and suggesting future IT developments/trends to managers and/or clients. Remain current on IT trends pertaining to their area of practice (e.g., Agile, DevOps, Cloud, Microservices, containers) Preparing documentation for the Project and for the Business users (using standard/non-standard templates) that includes but not limited to Installation, Configuration Guides, Design solutions, Process document for Operational support, Architecture diagrams and SOPs
... A186: MySQL DBA | B186: IS3 | C186: 7-9 Years | D186: =_xlfn.CONCAT(A186,"_",B186) -> MySQL DBA_IS3 | E186: 7 to 9 years of experience in MySQL database administration backed by ability to work on cloud database support. Expert in database administration Support and Administer database instances effectively, efficiently and independently Performing tasks related to installation and configuration, performance tuning, backup, recovery, security, patching, upgrades and high availability Resolve moderate to complex (P1, P2 and P3) incidents and problems effectively in a timely manner Providing 24X7 production support and available for escalations Responsible for performing root cause analysis and long term fix Responsible for implementation of medium to complex components of a project module, change request. Responsible for providing trend analysis to management team to enable them to make informed decisions Working in a cross cultural team and communicate effectively Mentoring and guiding junior team members Expertise in managing MySQL on medium to large systems Design solution for MySQL instance on Azure and AWS cloud. Provision MySQL instances on Azure and AWS in clustered and non-clustered configurations Ensure performance, security, and availability of databases Prepare documentations and specifications Handle common database procedures, such as upgrade, backup, recovery, migration, etc. Migrate database to cloud. Profile server resource usage, optimize and tweak as necessary Collaborate with other team members and stakeholders Migrate code, databse objects like table, views, stored procderues from MS SQL to MySQL Solutioning and architecture designing exposure Automation experience in the database support structure Ability to work with Azure and AWS Cloud (IaaS & PaaS), Cloud technologies Good team player and willingness to explore and learn new areas/technologies Basic knowledge of LINUX/Windows OS and its related commands Good knowledge of T-SQL and query tuning Good to have skills like Terraform, Ansible, Git, Jenkins Expertise in trouble shooting , pro-active monitoring, backup, restore/recovery and performance tuning Design, implement and manage MySQL High availability and Disaster recovery features Good analytical skills Flexible to work in shifts Good team player and willingness to explore and learn new areas/technologies.
A187: Cloud Security Analyst L1 | B187: IS2 | C187: 3-5 years | D187: Cloud_Security_Analyst_L1_IS2 | E187: Job Description: A Cloud Security Analyst L1 is responsible for ensuring the security of cloud-based systems and infrastructure. This candidate works to identify and mitigate security risks and implement security measures to protect against potential threats. The role involves working with cloud platforms such as Azure and AWS, to ensure that they are secure and compliant with the security policies. The Cloud security analyst works on security alerts, incidents, and providing incident response adhering to security practices and frameworks. This analyst will be part of the 24x7 Security Operations Centre (SOC) team. You will be required to work in shifts. Job Responsibilities: • Monitoring cloud-based systems and infrastructure for security breaches, managing such incidents. • Manage and support log collection, security scanning, intrusion detection, proxy, mail gateway and other security technologies. • Conducting regular security assessments of cloud-based systems and infrastructure to identify vulnerabilities, security misconfigurations and recommending remediation strategies. • Perform Malware Analysis • Review, triage security alerts, provide analysis, suggest remediation, track remediation. • Investigate and respond to security incidents (identifying, investigating, and responding to complex attacks) • Collaborating with other IT and security teams to ensure the overall security of the cloud infrastructure and ensure timely remediation of the security incidents. • Managing and maintaining security tools and technologies, such as Microsoft Defender for Cloud, Office365, AWS Security Hub, AWS Guardduty, AWS Config and other security-related software. • Keeping up to date with industry best practices and regulatory requirements related to cloud security and incorporating these into the organization's security policies and procedures. • Stay up to date with the latest security threats and trends in cloud security. • Conduct vulnerability assessments to identify and mitigate potential security risks. • Monitor and analyze security logs and alerts to identify security incidents and respond appropriately. • Good working experience and knowledge on SIEM technology (Microsoft Sentinel/ IBM QRadar/ ArcSight/ Securonix), Vulnerability management tools (NESSUS/Qualys), EDR and SOAR etc. • Ability to write technical documentation and present technical briefings to diverse audiences. • Strong understanding of threat landscape in terms of the tools, tactics, and techniques of threats employing both commodity and custom malware. • Responding to alerts from the various monitoring/detection systems and platforms within defined SLAs. • Knowledge on ITIL processes Minimum Qualification & Background: • 3-5 years of Information Security and cloud security experience. Minimum 5 years in a large 24x7 Security Operations Centre (SOC) and Cloud security tools and technologies • Proven experience in cloud security or a related field • Experience with cloud platforms such as AWS, Azure, and Google Cloud • Familiarity with industry standards such as ISO 27001, NIST, and SOC 2 • Knowledge of security technologies such as firewalls, IDS/IPS, SIEM, and endpoint protection • Should have minimum one cloud security certification (AZ-500, MS-500, SC-200, AWS Security Specialist, CCSP etc.,) • Excellent analytical and problem-solving skills • Strong communication and collaboration skills
A188: Cloud Security Analyst L2 | B188: IS2 | C188: 5-7 years | D188: Cloud_Security_Analyst_L2_IS2 | E188: Job Description: A Cloud Security Analyst L2 is responsible for ensuring the security of cloud-based systems and infrastructure. This candidate works to identify and mitigate security risks and implement security measures to protect against potential threats. The role involves working with cloud platforms such as Azure and AWS, to ensure that they are secure and compliant with the security policies. The Cloud security analyst works on threat intelligence, forensics support and incident response adhering to security practices and frameworks. This analyst will be part of the 24x7 Security Operations Centre (SOC) team. You will be required to work in shifts. Job Responsibilities: • Monitoring cloud-based systems and infrastructure for security breaches, managing such incidents. • Manage and support log collection, security scanning, intrusion detection, proxy, mail gateway and other security technologies. • Conducting regular security assessments of cloud-based systems and infrastructure to identify vulnerabilities, security misconfigurations and recommending remediation strategies. • Developing and implementing security policies, procedures, and controls for cloud-based systems and infrastructure. • Perform Malware Analysis • Review, triage security alerts, provide analysis, suggest remediation, track remediation. • Support Security Information and Event management (SIEM) solutions. Support integration with various devices. • Investigate and respond to security incidents (identifying, investigating, and responding to complex attacks) • Collaborating with other IT and security teams to ensure the overall security of the cloud infrastructure and ensure timely remediation of the security incidents. • Managing and maintaining security tools and technologies, such as Microsoft Defender for Cloud, Office365, AWS Security Hub, AWS Guardduty, AWS Config and other security-related software. • Keeping up to date with industry best practices and regulatory requirements related to cloud security and incorporating these into the organization's security policies and procedures. • Stay up to date with the latest security threats and trends in cloud security. • Conduct vulnerability assessments to identify and mitigate potential security risks. • Monitor and analyze security logs and alerts to identify security incidents and respond appropriately. • Good working experience and knowledge on SIEM technology (Microsoft Sentinel/ IBM QRadar/ ArcSight/ Securonix), Vulnerability management tools (NESSUS/Qualys), EDR and SOAR etc. • Ability to write technical documentation and present technical briefings to diverse audiences. • Strong understanding of threat landscape in terms of the tools, tactics, and techniques of threats employing both commodity and custom malware. • Responding to alerts from the various monitoring/detection systems and platforms within defined SLAs. • Knowledge on ITIL processes Minimum Qualification & Background: • 5-7 years of Information Security and cloud security experience. Minimum 5 years in a large 24x7 Security Operations Centre (SOC) and Cloud security tools and technologies • Several years of experience in cloud security, IT security, or a related field • Proven experience in cloud security or a related field • Experience with cloud platforms such as AWS, Azure, and Google Cloud • Familiarity with industry standards such as ISO 27001, NIST, and SOC 2 • Knowledge of security technologies such as firewalls, IDS/IPS, SIEM, and endpoint protection • Should have minimum one cloud security certification (AZ-500, MS-500, SC-200, AWS Security Specialist, CCSP etc.,) • Excellent analytical and problem-solving skills • Strong communication and collaboration skills
A189: Cloud Security Analyst L2/L3 | B189: IS3 | C189: 7-9 Years | D189: Cloud_Security_Analyst_L2/L3_IS3 | E189: Job Description: A Cloud Security Analyst L3 is responsible for ensuring the security of cloud-based systems and infrastructure. This candidate works to identify and mitigate security risks and implement security measures to protect against potential threats. The role involves working with cloud platforms such as Azure and AWS, to ensure that they are secure and compliant with the security policies. The Cloud security analyst works on threat intelligence, forensics support and incident response adhering to security practices and frameworks. This analyst will be part of the 24x7 Security Operations Centre (SOC) team. You will be required to work in shifts. Job Responsibilities: • Monitoring cloud-based systems and infrastructure for security breaches, managing such incidents. • Manage and support log collection, security scanning, intrusion detection, proxy, mail gateway and other security technologies. • Conducting regular security assessments of cloud-based systems and infrastructure to identify vulnerabilities, security misconfigurations and recommending remediation strategies. • Developing and implementing security policies, procedures, and controls for cloud-based systems and infrastructure. • Perform Malware Analysis • Review, triage security alerts, provide analysis, suggest remediation, track remediation. • Support Security Information and Event management (SIEM) solutions. Support integration with various devices. • Investigate and respond to security incidents (identifying, investigating, and responding to complex attacks) • Collaborating with other IT and security teams to ensure the overall security of the cloud infrastructure and ensure timely remediation of the security incidents. • Managing and maintaining security tools and technologies, such as Microsoft Defender for Cloud, Office365, AWS Security Hub, AWS Guardduty, AWS Config and other security-related software. • Keeping up to date with industry best practices and regulatory requirements related to cloud security and incorporating these into the organization's security policies and procedures. • Stay up to date with the latest security threats and trends in cloud security. • Conduct vulnerability assessments to identify and mitigate potential security risks. • Monitor and analyze security logs and alerts to identify security incidents and respond appropriately. • Implementation Knowledge on SIEM technology (Microsoft Sentinel/ IBM QRadar/ ArcSight/ Securonix), Vulnerability management tools (NESSUS/Qualys), EDR and SOAR etc. • Ability to write technical documentation and present technical briefings to diverse audiences. • Strong understanding of threat landscape in terms of the tools, tactics, and techniques of threats employing both commodity and custom malware. • Integration of Threat feeds • Responding to alerts from the various monitoring/detection systems and platforms within defined SLAs. • Knowledge on ITIL processes Minimum Qualification & Background: • 7-9 years of Information Security and cloud security experience. Minimum 5 years in a large 24x7 Security Operations Centre (SOC) and Cloud security tools and technologies • Several years of experience in cloud security, IT security, or a related field • Proven experience in cloud security or a related field • Experience with cloud platforms such as AWS, Azure, and Google Cloud • Familiarity with industry standards such as ISO 27001, NIST, and SOC 2 • Knowledge of security technologies such as firewalls, IDS/IPS, SIEM, and endpoint protection • Should have minimum one cloud security certification (AZ-500, MS-500, SC-200, AWS Security Specialist, CCSP etc.,) • Excellent analytical and problem-solving skills • Strong communication and collaboration skills
A190: Security Automation | B190: IS4 | C190: 7-9 Years | D190: Security_Automation_IS4 | E190: Job Description: Cyber Security Automation Engineer Cyber Security Automation Engineer will be responsible to develop information security and incident response workflows, procedures and best practices and publish them as playbooks in SOAR platform, Azure and AWS Platforms. The candidate is responsible for automating the alert responses, report automation of cloud tools like Microsoft Defender, AWS Security hub, and Microsoft Sentinel. The candidate will be working with the most up to date Cloud Security products to automate both deployments across multiple Enterprise level customers and the development of SOC as a Manage Service. You will be part of 24x7 Security Operations Centre (SOC) team. Job Scope • Perform SIEM and SOAR product support and implementation. • procedures and best practices and publish them as playbooks in SOAR platform, Azure and AWS Platforms. The candidate is responsible for automating the alert responses, report automation of cloud tools like Microsoft Defender, AWS Security hub, and Microsoft Sentinel • Develop and maintain automation solutions including Sentinel deployment scripts and pipelines (IAC) • Responsible for configuring and enforcing policies Azure policies, AWS control tower policies, AWS config etc., • Develop centralized repository to control the Analytics Rules, Playbooks and Automation rules • Develop Sentinel Playbooks, Workbooks, reports and playbooks. • Develop, implement, and execute standard procedures for the administration, content management, change management, version/patch management, and lifecycle management of the SIEM/SOAR platforms. • Develop information security and incident response workflows, procedures and best practices and publish them as playbooks in SOAR platform. • Should be able to write Cloudformation scripts, Python and Powershell scripts on need basis. • Worked along with Client on data onboarding and writing alerts, dashboards using the Kusto query Language. Requirement • Should be AZ-204 Certified or any other relevant certifications • Min of 5 years of exp in IT security • Min of 2 years of exp in SIEM and SOAR content development and testing • Prior experience Sentinel automation and rule creation using KQL, Sentinel Playbooks, Workbooks, Logic Apps, cloudformation template, terraform etc., • Exp in Implementation and support of any major SOAR platform and developing playbooks for automation. • Expertise in writing KQL searches and content use case development, well-versed with Azure architecture and design. • Exp with regular expressions and using regular expressions for data retrieval. • Strong knowledge of Windows, Linux, and UNIX OS • Azure DevOps and Pipelines, PowerShell, Python • ARM Templates, or Terraform (NICE TO HAVE) • Security Orchestration Automation and Response (SOAR)
A191: IAM /PAM Engineer L2 | B191: IS2 | C191: 5-7 years | D191: IAM_/PAM_Engineer_L2_IS2 | E191: JD – IAM Engineer Level -2 Job Description: IAM Engineer Level - 2 Summary Looking for candidate with 5 years of experience in IT and 3-5 years of experience in Identity and access Management (IAM) stream. Details of Experience: • Experience in operations and support of IAM tools • Handling critical incidents & issues. • Experience performing user administration tasks for IAM tools & azure AD. • Experience in MIM & azure AD preference • Experience with on-boarding of new applications user access management with required controls • Experience with creating and documenting IAM procedures/policies for new applications being on-boarded. • Excellent customer service in telephone or electronic interaction with clients • Experience performing user administration in a Windows Active Directory environment. • Basic knowledge of UNIX/Linux administration commands • Versatility, flexibility, and a willingness to work with constantly changing priorities • Ability to work independently and follow existing documentation/procedure flow • Experience with work-flow management tools (i.e. ServiceNow, Jira) would be preferred Location : India
A192: IAM /PAM Engineer L3 | B192: IS3 | C192: 7-9 Years | D192: IAM_/PAM_Engineer_L3_IS3 | E192: JD – IAM Engineer Level -3 Job Description: IAM Engineer Level - 3 Summary Looking for candidate with 7 years of experience in IT and 3-5 years of experience in Identity and access Management (IAM) stream. Details of Experience: • Experience in leading or guiding team. • Experience in handling critical incidents & issue related to IAM, SSO, PAM, etc. • Experience performing user administration tasks for IAM tools & azure AD. • MIM & azure AD preference • Experience with on-boarding of new applications user access management with required controls • Experience with creating and documenting IAM procedures/policies for new applications being on-boarded. • Excellent customer service in telephone or electronic interaction with clients • Experience performing user administration in a Windows Active Directory environment. • Basic knowledge of UNIX/Linux administration commands • Versatility, flexibility, and a willingness to work with constantly changing priorities • Ability to work independently and follow existing documentation/procedure flow • Experience with work-flow management tools (i.e. ServiceNow, Jira) would be preferred Location : India
A193: Cloud Security Governance | B193: IS4 | C193: 7-9 Years | D193: Cloud_Security_Governance_IS4 | E193: 1. Cloud Security Consultant: • 5 – 8 years stong experience in design and architecture of cloud security in one or more cloud platforms such as Amazon Web Services (AWS)/ Microsoft Azure/GCP • Should be able to assess the current state of clients’ cloud infrastructure, develop strategies and roadmap for improvement and advise in further securing the clients’ cloud environments and interaction with their on-premise infrastructure • Assist clients in developing strategies to secure their cloud environment by providing high value consultancy work • Designing, developing and building security reference architectures for public, private, and hybrid Cloud based systems within Amazon Web Services (AWS), Microsoft Azure, or other cloud providers. • Possess a firm understanding of security offerings within cloud platforms such as Amazon Web Services (AWS)/ Microsoft Azure/GCP platforms • Identifying, designing and deploying solutions to secure cloud usage, whether cloud-native or third party solutions • Lead security vision and strategy around cloud-based applications, across all types (including Infrastructure, Platform, and Software as a Service (IaaS/PaaS/SaaS) • Coordinate with various technology and security teams for all matters related to cloud security . • Analyze business requirements and transalate them to technical security solutions. • Experience with assessment, development, implementation, optimization, and documentation of a comprehensive and broad set of security technologies and processes (secure software development (Application Security), data protection, cryptography, key management, identity and access management (IAM), network security) within SaaS, IaaS, PaaS, and other cloud environments. • Experience working and responding to RFI/RFP requirements for global customers, writing SOW, effort estimation • Experience in performing Cloud Security Assessments. • Experience with Cloud security and governance tools, CASBs and server and network virtualization technologies. • Develop and execute strategies to increase Cloud Security knowledge across the organization and team. • Good understanding of IT Risk management,security frameworks and standards like COBIT, NIST 800 series, NIST CSF, ISO 31000, CSA-CCM, • Good understanding of regulatory compliance requirements such as SOX, GDPR, CCPA, PCI-DSS, FISMA, HIPAA, and HITRUST, RBI Cybersecurity requirements, DPA • Understanding of data protection & privacy laws in various countries like US, UK, Europe, APAC- Singapore, Australia, and India. • Excellent interpersonal and communication skills required to partner with other leaders across the business to identify opportunities and risks and develop and deliver technical security solutions that support business strategies. • Should be having any two security related certifications such as CISSP, CISM, CCSP, CCSK • Should have any one cloud related certification, such as AWS certified, Azure Certified • Good to have SOX, GDPR, Privacy training and certifications
A194: Security Manager | B194: IS5 | C194: 12-15 y ears | D194: Security_Manager_IS5 | E194: Cybersecurity Manager (Job Description): Cybersecurity Manager will be responsible for responsible for overall operations of Security Operations Centre. SOC is responsible to continuously monitor and analyze security threats and defends against potential security breaches; actively isolate and mitigate security risks. You lead a 24x7 Security Operations Centre (SOC) team. Job Responsibilities • Overall responsibility for the security operations including incident and response. • Responsible for team & vendor management, overall use of resources and initiation of corrective action where required for Security Operations Center • Provide leadership for the SOC operations. • Collaborate and follow up with internal and external teams on response, remediation of incidents. • Provide leadership & oversight for SOC operations. • Proactively identify and mitigate cyber security threats. • Threat intelligence and its integration. Integration of Threat feeds • Develop and maintain security SOC related procedures including incident response. • Responsible for developing SOC metrics, reports, dashboards, and presentation to management. Responsible for continuous improvement plans • Support internal and external audits. • Lead and participation in emergency SOC call from 24x7 SOC monitoring. • Respond to incidents by collecting, analyzing, and preserving digital evidence to assist with the Incident Responders in remediation of critical information security incidents. • Proactively mitigate cyber security risks and strengthen the attack detection and response processes. • Improve and challenge existing processes and procedures in an agile and fast-moving information security environment. • Threat Hunting • Perform threat management, threat modeling, identify threat vectors and develop use cases for security monitoring. • Responsible for integration of standard and non-standard logs with SOC platforms and tools • Manage and support the log collection, security scanning, intrusion detection, proxy, mail gateway and other security technologies. • Malware Analysis • Review, triage security alerts, provide analysis, suggest remediation, track remediation. • Support in resolving security incidents. • Investigate and respond to security incidents. • Monitor networks and systems for potential threats. • Knowledge of network data flows, ports, protocols, and other network and application services/technologies. • Responding to alerts from the various monitoring/detection systems and platforms within defined SLAs. • Current knowledge of security threat intelligence and recent attack vectors • Strong forensics analysis skills • Mentor and train team members • Knowledge on ITIL processes Minimum Qualification & Background: • 10-15 years of Information Security experience. Minimum 3 years as a SOC Manager or Lead in a large 24x7 Security Operations Centre (SOC) • Implementation knowledge on SIEM technology (IBM/HP/LogRhythm/Splunk/Sentinel), Vulnerability management tools (NESSUS/Qualys), EDR and SOAR etc. • Ability to write technical documentation and present technical briefings to diverse audiences. • Strong understanding of threat landscape in terms of the tools, tactics, and techniques of threats employing both commodity and custom malware. • Knowledge of Information security life cycle, policies, process, and standards. • Relevant security certification will be a plus. • Knowledge of AWS, Azure and GCP • Knowledge of current security threats, techniques, and landscape. • Security events, incident review and triage experience with Endpoint Detection and Response (EDR) tools • Experience and knowledge related to the configuration and maintenance of security monitoring and reporting platforms. • Ability to conduct detailed analysis of various security related events like Phishing, Spoofing, Ransomware and SQL Injections etc. • Incident Response experience (identifying, investigating, and responding to complex attacks) • Experience with threat hunting.
A195: ADO | B195: IS4 | C195: 8-12 years | D195: Azure DevOps & CICD_IS4 | E195: Roles: Azure DevOps Technical Lead Should have 5+ years of relevant hands-on experience in DevOps implementation. Total years of experience of 8-12 years Responsibilities: • Design and Architect DevOps strategy for Continuous Integration (“CI"), Continuous Deployment ("CD") process for applications hosted in Cloud and On-prem servers. • Create Ansible play book for configuration management as per the requirement. • Strategize DevOps CI/CD process based on project requirements. • Create pipelines and repositories in ADO for application & infrastructure deployment as per the requirement with adherence to Standards. • Coordinate & work with application and infrastructure team to ensure pipelines and repositories are working as expected in cloud during production or major releases if any. • Generate monthly and/or quarterly reports on repositories details and update customers periodically. • Must have scripting experience in Azure DevOps pipeline creation with Yaml, JSON & API. • Terminate Azure Dev Ops access for the users as per the SOX compliance & access management policy. • Create and provide access for the users to the repositories & pipeline as per the Access management policy. • Create and update knowledge management document on known issues with resolutions if any. • Deploy application to AWS and On-Premise servers using Azure DevOps Pipelines
A196: ADO | B196: IS3 | C196: 7-10 years | D196: Azure DevOps & CICD_IS3 | E196: Roles: Senior Azure DevOps Should have 3 to 5 years of relevant hands-on experience in DevOps implementation. Total experience can be 7-10 years. Responsibilities: • Design and Architect DevOps strategy for Continuous Integration (“CI"), Continuous Deployment ("CD") process for applications hosted in Cloud and On-prem servers. • Create Ansible play book for configuration management as per the requirement. • Strategize DevOps CI/CD process based on project requirements. • Create pipelines and repositories in ADO for application & infrastructure deployment as per the requirement with adherence to Standards. • Coordinate & work with application and infrastructure team to ensure pipelines and repositories are working as expected in cloud during production or major releases if any. • Generate monthly and/or quarterly reports on repositories details and update customers periodically. • Must have scripting experience in Azure DevOps pipeline creation with Yaml, JSON & API. • Terminate Azure Dev Ops access for the users as per the SOX compliance & access management policy. • Create and provide access for the users to the repositories & pipeline as per the Access management policy. • Create and update knowledge management document on known issues with resolutions if any. • Deploy application to AWS and On-Premise servers using Azure DevOps Pipelines
A197: ADO | B197: IS3 | C197: 7-10 years | D197: webMethods_IS3 | E197: Roles: Senior webMethods Administrator & Support Lead Should have 5 years of hands-on experience in webMethods Administrator. Total experience of 7-10 years. • SOA Admin (Web Methods Administration and Support). • Will be responsible for the upgrading of Web Methods application servers from existing 10.5 version to 10.11 version and identifies the deprecated functions. • Responsible for installation and maintenance of web Methods servers on AWS Cloud and troubleshoot of any infra related issues. • Develops the scripts for auto installation of web Methods components like Integration Server, Universal Messaging, Terracotta and MyWebMethods Server. • Perform daily health check of web Methods Production servers and sharing the report. • Diagnoses the application server issues across each environment, resolves them on priority basis and takes prevention actions as required. • Coordinate with AWS Infrastructure team & Vendor by supporting Operating System. • Kernel upgrades and to perform post patching validations if any. • Work with other application teams & vendors to ensure the API are integrated • SOA Web Methods as per best practice.
A198: Service Manager | B198: IS4 | C198: 10-12 years | D198: M365 Service_Project Manager_IS4 | E198: • Facilitate the Quarterly Business Review (QBR) process • Monitor and communicate issues and risks • Execute SLA achievement
... A209: Agile Project Manager cum Product Owner (India) -Offshore | B209: IS4 | C209: 8-10 years | D209: Agile Project Manager cum Product Owner | E209: We are seeking a highly skilled and experienced Agile Project Manager cum Product Owner to lead our Android mobile app development and AEM project. The successful candidate will be responsible for ensuring that the project is completed on time, within budget, and to the required quality standards. Responsibilities: • Facilitate daily stand-up meetings, sprint planning meetings, sprint review meetings, and retrospective meetings. • Define and prioritize the product backlog, ensuring that it aligns with the product vision and roadmap. • Work closely with customers and stakeholders to understand their needs and gather requirements. • Create and maintain user stories, epics, and acceptance criteria in the product backlog • Collaborate with the development team to ensure that the user stories are properly estimated and understood. • Collaborate with cross-functional teams to define project scope, goals, and deliverables. • Manage and track project progress, identify potential risks and issues, and develop mitigation plans. • Ensure that the project is delivered on time, within budget, and to the required quality standards. • Communicate project status, progress, and issues to stakeholders and senior management. • Foster a positive team environment and promote effective communication, collaboration, and teamwork. • Ensure that project documentation, including requirements, specifications, and test plans, are complete, accurate, and up to date. Requirements: • Bachelor’s degree in computer science, Engineering, or related field. • At least 5 years of experience in software project management, with a focus on Adobe experience manager and mobile app development projects using SCRUM Agile • Ability to gather and analyze requirements and create user stories and acceptance criteria. • Strong understanding of the software development life cycle and best practices. • Must have good experience in Adobe Campaign • Must have good experience in Analytic (Google Analytic and Adobe Analytic) • Excellent communication, collaboration, and leadership skills. • Proven ability to manage multiple projects and priorities simultaneously. • Strong problem-solving and decision-making skills. • Experience with project management tools, such as Azure Dashboard or Jira • Good understanding on Azure DevOps CI/CD process • Certified Scrum Master (CSM) or equivalent Agile certification is preferred. • Experience with Android app development is a plus • Experience in development using Adobe Experience Manager is a plus
A210: DB Architect | B210: IS4 | E210: Define Application Architecture •Perform Application Architecture Review •Store Procedure Reviews •Performance Review •Production Issues Support & Troubleshooting •Review Documentations created by DBA Support Team •Activities related to Clustering •Deployment related to Production Environments •SQL Server On Premise & •DB Partition Activities •Datawarehouse Integrations •System Integrations •Data Processing as per system requirements •SQL Version Upgrades •Design & Review Jobs, Tables, Partitions Functions & Groups
A211: AMS-Project Manager | B211: IS4 | E211: ITC is looking for a Project Manager to manage a Application Maintenance and Support project with 10-12 years of experience across a range of levels from different backgrounds and with various skills and expertise. In this role who can work with Customers, Delivery team. Certifications Professional certification on Project/Program Management is highly desirable ITSM Certification Roles and Responsibilities Project Manager should have good experience in managing large AMS programs and running managed service delivery. The Project Manager serves a key upfront role on these assessments by ensuring that customers are choosing the correct tools and programs throughout the planning and execution of their migration, as well as serving as a contact person to reduce friction and roadblocks throughout the customer’s migration journey and running efficient service delivery. Gather requirements from customers regarding desired outcomes of the assessment to ensure the appropriate tools and teams are included. Dealing with stakeholders, plan, organize, schedule, control, and monitor projects to ensure timely completion, cost effectiveness, and customer satisfaction. Proactively identifies potential delivery issues and drives resolution to avoid customer impact. Always look for area of opportunity for automation adoption and optimize resource efforts, efficiency and drive ROI Identifies scope changes from the original plan or agreement and escalates to the management team. Setting up the team and mentoring them Works directly with technical team and ensure project success and managing the team. Develop, maintain, and manage relationships with client executives and engagement sponsors and provides complex metrics and reporting support to all relevant stakeholders. Knowledge working closely with ServiceNow/Jira or any other project management software. Excellent oral and written communications skills as necessary to communicate, negotiate, advice, or resolve issues that are highly complex including the ability to communicate technical information to nontechnical users effectively. Manage the intake process for all new Migration assessments. Position and propose the inclusion of partners for an assessment, when applicable. Provide high-level demonstrations & overviews of migration tools to outline options to internal and external customers. Provide a single point of escalation for teams needing Migration assistance, or for high profile assessments.
A212: Service Delivery Manager | B212: I5+ | C212: 12-18 Years | D212: Service Delivery Manager-Regions | E212: Role Service Delivery Managers- Regions Relevant Experience 8 Years in the Role- At least 5+ projects experience as a Service Manager Overall Experience 12-18 Years – Covering all areas of SDLC ( In Support project Roles) Experience Details • Experience in managing Development and Application Support projects with legacy and digital apps and other IT Programs to deliver within Schedule, Cost & Quality with 50+member team. • Well versed with ITIL processes and able to design and implement a service life cycle. • Well versed with quality audits and metrics related to service delivery • Experience in transition management (taking over services from other vendors) • Experience in handling projects in Microsoft stack / Java / Legacy system / Databases / Integration / Testing • Responsible for Service Delivery with consistent high level quality, on time and within budget. Proven good track record: leadership and interpersonal skills with High level commitments to deliver end to end customer driven solutions • Expectational customer-facing skills, expertise in people management and ability to lead large diverse teams. • Good experience in driving Process Improvement initiative leveraging latest technologies. • Proficiency handling portfolio growth initiatives and experience around working on proposals. • Good Experience in Customer Interaction and Managing stakeholders and submit periodic project status reports to confirm project progress to the customer. • Proficiency in Support operations handling, Problem Management, Resource Management and Risk Management. • In-depth knowledge of escalation procedures, incident management, and other disciplines related to service delivery • Experience in project level activities of handling PMR, Audits and budget handling. • Retail domain experience is good to have • Good understanding of Project, Program and Financial management • Coach and Mentor the Project Managers • Readiness to demonstrate proactive mind set • Excellent verbal and written communication skills • PMP or equivalent • Scrum Master/Equivalent

Sheet SAP AMS
A1: Skill | B1: Grade | C1: JD Ref ID | D1: JD | E1: Panel
A2: SAP SD, LE | B2: IS1 | C2: =_xlfn.CONCAT(A2,"_",B2) -> SAP SD, LE_IS1 | D2: Good communication and interpersonal skills. Should be able to learn quickly on the new areas / cross functional areas Experience either worked in the SAP AMS / SAP config and development track Experince in SAP SD mainly covering Understanding on Sales Process, Contract management, Pricing concepts, OTC, Partner Determination, Text Management, Pricing, Taxes, Billing, Credit Management, Back Orders, and Master Data Management (MDM). Experience in configuring Master Data, Document Types (Sales Order Types, Delivery Documents, Billing Documents, Credit and debit memo, etc.) including special order types (Third Party Processing, Consignment Processing, Inter-Company Billing and Inter-company stock transfers), Availability Check, Material Listing/Exclusion, Rebate processing, Deliveries and Post Goods Issues. Experience Required : 2-6 years of experience with 1 implementation on SAP ERP implementation experience and 1 AMS experience worked with global customers Good understanding of SAP Fiori apps Experience in SAP cross-functional areas such as FI/CO, MM/PP Good understanding of all types of order processing models, including B2B, B2C, EDI would be added advantage Experience in project cut-over, successful go-live and client handling during PGLS and alignment with AMS teams will be valued. Good knowledge in the below areas : Electronic data interchange (EDI) : EDI Mapping Integration: Materials Management(MM), Finance, Transportation Management, Management Accounting Experience of third-party application integration using SAP PI/PO such as WM etc.
A3: SAP SD, LE | B3: IS2 | C3: =_xlfn.CONCAT(A3,"_",B3) -> SAP SD, LE_IS2 | D3: Good communication and interpersonal skills. Should be able to learn quickly on the new areas / cross functional areas Experience either worked in the SAP AMS / SAP config and development track Experince in SAP SD mainly covering Understanding on Sales Process, Contract management, Pricing concepts, OTC, Partner Determination, Text Management, Pricing, Taxes, Billing, Credit Management, Back Orders, and Master Data Management (MDM). Experience in configuring Master Data, Document Types (Sales Order Types, Delivery Documents, Billing Documents, Credit and debit memo, etc.) including special order types (Third Party Processing, Consignment Processing, Inter-Company Billing and Inter-company stock transfers), Availability Check, Material Listing/Exclusion, Rebate processing, Deliveries and Post Goods Issues. Experience Required : 2-6 years of experience with 1 implementation on SAP ERP implementation experience and 1 AMS experience worked with global customers Good understanding of SAP Fiori apps Experience in SAP cross-functional areas such as FI/CO, MM/PP Good understanding of all types of order processing models, including B2B, B2C, EDI would be added advantage Experience in project cut-over, successful go-live and client handling during PGLS and alignment with AMS teams will be valued. Good knowledge in the below areas : Electronic data interchange (EDI) : EDI Mapping Integration: Materials Management(MM), Finance, Transportation Management, Management Accounting Experience of third-party application integration using SAP PI/PO such as WM etc.
A4: SAP SD, LE | B4: IS3 | C4: =_xlfn.CONCAT(A4,"_",B4) -> SAP SD, LE_IS3 | D4: Independently take up and participate in Business workshops, Design End to End solutions . Extensive experience either worked in the SAP AMS / SAP config and development track The candidate must have strong design and implementation knowledge of SAP SD mainly covering Understanding on Sales Process, Contract management, Pricing concepts, OTC, Partner Determination, Text Management, Pricing, Taxes, Billing, Credit Management, Back Orders, and Master Data Management (MDM). Strong experience in configuring Master Data, Document Types (Sales Order Types, Delivery Documents, Billing Documents, Credit and debit memo, etc.) including special order types (Third Party Processing, Consignment Processing, Inter-Company Billing and Inter-company stock transfers), Availability Check, Material Listing/Exclusion, Rebate processing, Deliveries and Post Goods Issues. Exceptional communication and interpersonal skills. Experience Required : Minimum 6-10 years of experience with 1-2 implementation on SAP ERP implementation experience and 2 AMS experience worked with global customers Good understanding of SAP Fiori apps Experience in SAP cross-functional areas such as FI/CO, MM/PP Strong understanding of all types of order processing models, including B2B, B2C, EDI. Business knowledge and solution design experience in all areas of the Order To Cash cycle, including order processing and credit management Proven experience in project cut-over, successful go-live and client handling during PGLS and alignment with AMS teams will be valued. Should also have additional knowledge in the below areas : Electronic data interchange (EDI) : EDI Mapping Integration: Materials Management(MM), Finance, Transportation Management, Management Accounting Experience of third-party application integration using SAP PI/PO such as WM etc.
A5: SAP SD, LE | B5: IS4 | C5: =_xlfn.CONCAT(A5,"_",B5) -> SAP SD, LE_IS4 | D5: Independently take up and participate in Business workshops, Design End to End solutions with SAP Activate, Agile and DevOps methodologies. Extensive experience either in leading the SAP AMS / leading the SAP config and development track The candidate must have strong design and implementation knowledge of SAP SD mainly covering Understanding on Sales Process, Contract management, Pricing concepts, OTC, Partner Determination, Text Management, Pricing, Taxes, Billing, Credit Management, Back Orders, and Master Data Management (MDM). Strong experience in configuring Master Data, Document Types (Sales Order Types, Delivery Documents, Billing Documents, Credit and debit memo, etc.) including special order types (Third Party Processing, Consignment Processing, Inter-Company Billing and Inter-company stock transfers), Availability Check, Material Listing/Exclusion, Rebate processing, Deliveries and Post Goods Issues. Exceptional communication and interpersonal skills. Experience Required : Minimum 10 years of experience with 2-3 implementation on SAP ERP implementation experience Good understanding of SAP Fiori apps Experience in SAP cross-functional areas such as FI/CO, MM/PP Strong understanding of all types of order processing models, including B2B, B2C, EDI. Business knowledge and solution design experience in all areas of the Order To Cash cycle, including order processing and credit management Proven experience in project cut-over, successful go-live and client handling during PGLS and alignment with AMS teams will be valued. Should also have additional knowledge in the below areas : Electronic data interchange (EDI) : EDI Mapping Integration: Materials Management(MM), Finance, Transportation Management, Management Accounting Experience of third-party application integration using SAP PI/PO such as WM etc.
C6: =_xlfn.CONCAT(G6,"_",H6) -> _
A7: MM, WM + SRM | B7: IS1 | C7: =_xlfn.CONCAT(A7,"_",B7) -> MM, WM + SRM_IS1 | D7: Experience either in wored in SAP AMS / SAP config and development track Good communication and interpersonal skills. Should be able to learn quickly on the new areas / cross functional areas Should possess natural analytical way of thinking and troubleshooting issues. Technical analysis and documentation of SAP MM/WM application, and it’s integration with other SAP applications like SAP TM, SAP SD, SAP FI and 3rd party applications. Experience Required : Experienced in the areas of SAP ERP MM-PO & MM-IM including Purchase Requisition and Purchase Orders, set up of stock transport orders, Purchase Pricing, PO Release and approvals, Inventory movements and integration to SAP SD (Sales and distribution) SAP Finance, SAP WM (Warehouse Management) etc. Inbound and Outbound IDOCs and Interfaces, Purchasing Output Management and Forms. Understanding in Master data related to procurement like materials, Info records, Business Partners etc. Good understanding of SAP Fiori apps Experienced with 3rd party interfaces and integration. Experience in project cut-over, successful go-live and client handling during PGLS and alignment with AMS teams will be valued. Experience in Third party integration – Movilizer, Barcoding, 3rd party applications would be added advantage
A8: MM, WM + SRM | B8: IS2 | C8: =_xlfn.CONCAT(A8,"_",B8) -> MM, WM + SRM_IS2 | D8: Experience either in wored in SAP AMS / SAP config and development track Good communication and interpersonal skills. Should be able to learn quickly on the new areas / cross functional areas Should possess natural analytical way of thinking and troubleshooting issues. Technical analysis and documentation of SAP MM/WM application, and it’s integration with other SAP applications like SAP TM, SAP SD, SAP FI and 3rd party applications. Experience Required : Experienced in the areas of SAP ERP MM-PO & MM-IM including Purchase Requisition and Purchase Orders, set up of stock transport orders, Purchase Pricing, PO Release and approvals, Inventory movements and integration to SAP SD (Sales and distribution) SAP Finance, SAP WM (Warehouse Management) etc. Inbound and Outbound IDOCs and Interfaces, Purchasing Output Management and Forms. Understanding in Master data related to procurement like materials, Info records, Business Partners etc. Good understanding of SAP Fiori apps Experienced with 3rd party interfaces and integration. Experience in project cut-over, successful go-live and client handling during PGLS and alignment with AMS teams will be valued. Experience in Third party integration – Movilizer, Barcoding, 3rd party applications would be added advantage
A9: MM, WM + SRM | B9: IS3 | C9: =_xlfn.CONCAT(A9,"_",B9) -> MM, WM + SRM_IS3 | D9: Independently take up and participate in Business workshops, Design End to End solutions Extensive experience either in wored in SAP AMS / SAP config and development track Should possess natural analytical way of thinking and troubleshooting issues. Good communication and interpersonal skills. Technical analysis and documentation of SAP MM/WM application, and it’s integration with other SAP applications like SAP TM, SAP SD, SAP FI and 3rd party applications. Experience Required : Experienced in the areas of SAP ERP MM-PO & MM-IM including Purchase Requisition and Purchase Orders, set up of stock transport orders, Purchase Pricing, PO Release and approvals, Inventory movements and integration to SAP SD (Sales and distribution) SAP Finance, SAP WM (Warehouse Management) etc. Inbound and Outbound IDOCs and Interfaces, Purchasing Output Management and Forms. Understanding in Master data related to procurement like materials, Info records, Business Partners etc. Good understanding of SAP Fiori apps Experienced with 3rd party interfaces and integration. 6-10 years overall experience and Implementation and delivery experience, which should include at least 1-2 full project lifecycles on SAP ERP and 2 AMS support experience worked across global customers Proven experience in project cut-over, successful go-live and client handling during PGLS and alignment with AMS teams will be valued. Third party integration – Movilizer, Barcoding, 3rd party applications
A10: MM, WM + SRM | B10: IS4 | C10: =_xlfn.CONCAT(A10,"_",B10) -> MM, WM + SRM_IS4 | D10: Independently take up and participate in Business workshops, Design End to End solutions with SAP Activate, Agile and DevOps methodologies. Extensive experience either in leading the SAP AMS / leading the SAP config and development track Requirements gathering, project planning and management, solution design, configuration and customization of SAP ERP MM-PO and MM-IM, WM Should possess natural analytical way of thinking and troubleshooting issues. Exceptional communication and interpersonal skills. Technical analysis and documentation of SAP MM/WM application, and it’s integration with other SAP applications like SAP TM, SAP SD, SAP FI and 3rd party applications. Experience Required : Highly experienced in the areas of SAP ERP MM-PO & MM-IM including Purchase Requisition and Purchase Orders, set up of stock transport orders, Purchase Pricing, PO Release and approvals, Inventory movements and integration to SAP SD (Sales and distribution) SAP Finance, SAP WM (Warehouse Management) etc. Inbound and Outbound IDOCs and Interfaces, Purchasing Output Management and Forms. Understanding in Master data related to procurement like materials, Info records, Business Partners etc. Good understanding of SAP Fiori apps Experienced with 3rd party interfaces and integration. 10+ years overall experience and Implementation and delivery experience, which should include at least 2-3 full project lifecycles on SAP ERP. Proven experience in project cut-over, successful go-live and client handling during PGLS and alignment with AMS teams will be valued. Third party integration – Movilizer, Barcoding, 3rd party applications
A11: MM, WM + SRM | B11: IS5 | C11: =_xlfn.CONCAT(A11,"_",B11) -> MM, WM + SRM_IS5 | D11: Independently take up and participate in Business workshops, Design End to End solutions with SAP Activate, Agile and DevOps methodologies. Extensive experience either in leading the SAP AMS / leading the SAP config and development track Requirements gathering, project planning and management, solution design, configuration and customization of SAP ERP MM-PO and MM-IM, WM Should possess natural analytical way of thinking and troubleshooting issues. Exceptional communication and interpersonal skills. Technical analysis and documentation of SAP MM/WM application, and it’s integration with other SAP applications like SAP TM, SAP SD, SAP FI and 3rd party applications. Experience Required : Highly experienced in the areas of SAP ERP MM-PO & MM-IM including Purchase Requisition and Purchase Orders, set up of stock transport orders, Purchase Pricing, PO Release and approvals, Inventory movements and integration to SAP SD (Sales and distribution) SAP Finance, SAP WM (Warehouse Management) etc. Inbound and Outbound IDOCs and Interfaces, Purchasing Output Management and Forms. Understanding in Master data related to procurement like materials, Info records, Business Partners etc. Good understanding of SAP Fiori apps Experienced with 3rd party interfaces and integration. 10+ years overall experience and Implementation and delivery experience, which should include at least 2-3 full project lifecycles on SAP ERP. Proven experience in project cut-over, successful go-live and client handling during PGLS and alignment with AMS teams will be valued. Third party integration – Movilizer, Barcoding, 3rd party applications
A13: FI, CO | B13: IS1 | C13: =_xlfn.CONCAT(A13,"_",B13) -> FI, CO_IS1 | D13: Should possess natural analytical way of thinking and troubleshooting issues. Good communication and interpersonal skills. Should be able to learn quickly on the new areas / cross functional areas Pls look for unique roles as follows : 1. SAP FICO, 2. SAP Treasury Managemant, 3. SAP Cash Management, 4. SAP Central Finance Experience Required : 2-6 years of experience with 1 implementation in SAP ERP and 1 AMS expereince worked with Global customer Experience in SAP cross-functional areas such as SD, MM/PP, PS Good knowledge in all types of order processing models, including B2B, B2C, EDI. Experience in project cut-over, successful go-live and client handling during PGLS and alignment with AMS teams will be valued. Experience in FI: G/L, AP, AR, Treasury, Assets, Closing and Reporting, CO: CCA, PCA, Internal order, CO-PA, CO-PC Experience in Controlling submodules like CO-Product Costing and CO-Profitability Analysis and CO-Profit center Accounting is must. SAP Functional configuration expertise in General Ledger (FI- GL), Controlling (CO), Accounts Receivable (AR), Accounts Payable (AP), Asset Accounting (AA), Project Systems (PS) Profitability Analysis (PA), New GL, Experience in Financial Month end Activity, Financial Closing Cockpit(Task template, Task list) and Intercompany reconciliation process. Good to have knowledge in Fiori Apps, Fiori Launchpad, Fiori Launchpad Designer configuration & feature and Fiori application types.
A14: FI, CO | B14: IS2 | C14: =_xlfn.CONCAT(A14,"_",B14) -> FI, CO_IS2 | D14: Should possess natural analytical way of thinking and troubleshooting issues. Good communication and interpersonal skills. Should be able to learn quickly on the new areas / cross functional areas Pls look for unique roles as follows : 1. SAP FICO, 2. SAP Treasury Managemant, 3. SAP Cash Management, 4. SAP Central Finance Experience Required : 2-6 years of experience with 1 implementation in SAP ERP and 1 AMS expereince worked with Global customer Experience in SAP cross-functional areas such as SD, MM/PP, PS Good knowledge in all types of order processing models, including B2B, B2C, EDI. Experience in project cut-over, successful go-live and client handling during PGLS and alignment with AMS teams will be valued. Experience in FI: G/L, AP, AR, Treasury, Assets, Closing and Reporting, CO: CCA, PCA, Internal order, CO-PA, CO-PC Experience in Controlling submodules like CO-Product Costing and CO-Profitability Analysis and CO-Profit center Accounting is must. SAP Functional configuration expertise in General Ledger (FI- GL), Controlling (CO), Accounts Receivable (AR), Accounts Payable (AP), Asset Accounting (AA), Project Systems (PS) Profitability Analysis (PA), New GL, Experience in Financial Month end Activity, Financial Closing Cockpit(Task template, Task list) and Intercompany reconciliation process. Good to have knowledge in Fiori Apps, Fiori Launchpad, Fiori Launchpad Designer configuration & feature and Fiori application types.
A15: FI, CO | B15: IS3 | C15: =_xlfn.CONCAT(A15,"_",B15) -> FI, CO_IS3 | D15: Independently take up and participate in Business workshops, Design End to End solutions with SAP Should possess natural analytical way of thinking and troubleshooting issues. Good communication and interpersonal skills. Pls look for unique roles as follows : 1. SAP FICO, 2. SAP Treasury Managemant, 3. SAP Cash Management, 4. SAP Central Finance Experience Required : Minimum 6-10 years of experience with 1-2 implementation in SAP ERP and 3 AMS expereince worked with Global customer Experience in SAP cross-functional areas such as SD, MM/PP, PS Strong understanding of all types of order processing models, including B2B, B2C, EDI. Proven experience in project cut-over, successful go-live and client handling during PGLS and alignment with AMS teams will be valued. Strong experience in FI: G/L, AP, AR, Treasury, Assets, Closing and Reporting, CO: CCA, PCA, Internal order, CO-PA, CO-PC Very good experience in Controlling submodules like CO-Product Costing and CO-Profitability Analysis and CO-Profit center Accounting is must. SAP Functional configuration expertise in General Ledger (FI- GL), Controlling (CO), Accounts Receivable (AR), Accounts Payable (AP), Asset Accounting (AA), Project Systems (PS) Profitability Analysis (PA), New GL, Experience in Financial Month end Activity, Financial Closing Cockpit(Task template, Task list) and Intercompany reconciliation process. Experience with Simple Finance / Central Finance exposure will be given preference Project experience activities to include preparation, synchronization, conversion and post processing, table mapping for HANA, comprehensive knowledge of BP roles and functionality of S4 HANA Finance is preferred. Should have an overview of Deployment option for S4H. Good to have knowledge in Fiori Apps, Fiori Launchpad, Fiori Launchpad Designer configuration & feature and Fiori application types.
A16: FI, CO | B16: IS4 | C16: =_xlfn.CONCAT(A16,"_",B16) -> FI, CO_IS4 | D16: Independently take up and participate in Business workshops, Design End to End solutions with SAP Extensive experience in delivering Agile, DevOps, Activate methology Extensive experience either in leading the SAP AMS / leading the SAP config and development track Should possess natural analytical way of thinking and troubleshooting issues. Exceptional communication and interpersonal skills. Understanding new business strategies, providing recommendations for automated solutions to support new strategies Pls look for unique roles as follows : 1. SAP FICO, 2. SAP Treasury Managemant, 3. SAP Cash Management, 4. SAP Central Finance Experience Required : Minimum 10 years of experience with 2-3 implementation on S/4Hana implementation experience Experience in SAP cross-functional areas such as SD, MM/PP, PS Strong understanding of all types of order processing models, including B2B, B2C, EDI. Proven experience in project cut-over, successful go-live and client handling during PGLS and alignment with AMS teams will be valued. Strong experience in FI: G/L, AP, AR, Treasury, Assets, Closing and Reporting, CO: CCA, PCA, Internal order, CO-PA, CO-PC Very good experience in Controlling submodules like CO-Product Costing and CO-Profitability Analysis and CO-Profit center Accounting is must. SAP Functional configuration expertise in General Ledger (FI- GL), Controlling (CO), Accounts Receivable (AR), Accounts Payable (AP), Asset Accounting (AA), Project Systems (PS) Profitability Analysis (PA), New GL, Experience in Financial Month end Activity, Financial Closing Cockpit(Task template, Task list) and Intercompany reconciliation process. Experience with Simple Finance / Central Finance exposure will be given preference Project experience activities to include preparation, synchronization, conversion and post processing, table mapping for HANA, comprehensive knowledge of BP roles and functionality of S4 HANA Finance is preferred. Should have an overview of Deployment option for S4H. Good to have knowledge in Fiori Apps, Fiori Launchpad, Fiori Launchpad Designer configuration & feature and Fiori application types.
A17: FI, CO | B17: IS5 | C17: =_xlfn.CONCAT(A17,"_",B17) -> FI, CO_IS5 | D17: Independently take up and participate in Business workshops, Design End to End solutions with SAP Extensive experience in delivering Agile, DevOps, Activate methology Extensive experience either in leading the SAP AMS / leading the SAP config and development track Should possess natural analytical way of thinking and troubleshooting issues. Exceptional communication and interpersonal skills. Understanding new business strategies, providing recommendations for automated solutions to support new strategies Pls look for unique roles as follows : 1. SAP FICO, 2. SAP Treasury Managemant, 3. SAP Cash Management, 4. SAP Central Finance Experience Required : Minimum 10 years of experience with 2-3 implementation on S/4Hana implementation experience Experience in SAP cross-functional areas such as SD, MM/PP, PS Strong understanding of all types of order processing models, including B2B, B2C, EDI. Proven experience in project cut-over, successful go-live and client handling during PGLS and alignment with AMS teams will be valued. Strong experience in FI: G/L, AP, AR, Treasury, Assets, Closing and Reporting, CO: CCA, PCA, Internal order, CO-PA, CO-PC Very good experience in Controlling submodules like CO-Product Costing and CO-Profitability Analysis and CO-Profit center Accounting is must. SAP Functional configuration expertise in General Ledger (FI- GL), Controlling (CO), Accounts Receivable (AR), Accounts Payable (AP), Asset Accounting (AA), Project Systems (PS) Profitability Analysis (PA), New GL, Experience in Financial Month end Activity, Financial Closing Cockpit(Task template, Task list) and Intercompany reconciliation process. Experience with Simple Finance / Central Finance exposure will be given preference Project experience activities to include preparation, synchronization, conversion and post processing, table mapping for HANA, comprehensive knowledge of BP roles and functionality of S4 HANA Finance is preferred. Should have an overview of Deployment option for S4H. Good to have knowledge in Fiori Apps, Fiori Launchpad, Fiori Launchpad Designer configuration & feature and Fiori application types.
A19: FI+TRM Finance | B19: IS2 | C19: =_xlfn.CONCAT(A19,"_",B19) -> FI+TRM Finance_IS2 | D19: Should possess natural analytical way of thinking and troubleshooting issues. Good communication and interpersonal skills. Should be able to learn quickly on the new areas / cross functional areas Pls look for unique roles as follows : 1. SAP FICO, 2. SAP Treasury Managemant, 3. SAP Cash Management, 4. SAP Central Finance Experience Required : 2-6 years of experience with 1 implementation in SAP ERP and 1 AMS expereince worked with Global customer Experience in SAP cross-functional areas such as SD, MM/PP, PS Good knowledge in all types of order processing models, including B2B, B2C, EDI. Experience in project cut-over, successful go-live and client handling during PGLS and alignment with AMS teams will be valued. Experience in FI: G/L, AP, AR, Treasury, Assets, Closing and Reporting, CO: CCA, PCA, Internal order, CO-PA, CO-PC Experience in Controlling submodules like CO-Product Costing and CO-Profitability Analysis and CO-Profit center Accounting is must. SAP Functional configuration expertise in General Ledger (FI- GL), Controlling (CO), Accounts Receivable (AR), Accounts Payable (AP), Asset Accounting (AA), Project Systems (PS) Profitability Analysis (PA), New GL, Experience in Financial Month end Activity, Financial Closing Cockpit(Task template, Task list) and Intercompany reconciliation process. Good to have knowledge in Fiori Apps, Fiori Launchpad, Fiori Launchpad Designer configuration & feature and Fiori application types.
A20: FI+TRM Finance | B20: IS3 | C20: =_xlfn.CONCAT(A20,"_",B20) -> FI+TRM Finance_IS3 | D20: Independently take up and participate in Business workshops, Design End to End solutions with SAP Should possess natural analytical way of thinking and troubleshooting issues. Good communication and interpersonal skills. Pls look for unique roles as follows : 1. SAP FICO, 2. SAP Treasury Managemant, 3. SAP Cash Management, 4. SAP Central Finance Experience Required : Minimum 6-10 years of experience with 1-2 implementation in SAP ERP and 3 AMS expereince worked with Global customer Experience in SAP cross-functional areas such as SD, MM/PP, PS Strong understanding of all types of order processing models, including B2B, B2C, EDI. Proven experience in project cut-over, successful go-live and client handling during PGLS and alignment with AMS teams will be valued. Strong experience in FI: G/L, AP, AR, Treasury, Assets, Closing and Reporting, CO: CCA, PCA, Internal order, CO-PA, CO-PC Very good experience in Controlling submodules like CO-Product Costing and CO-Profitability Analysis and CO-Profit center Accounting is must. SAP Functional configuration expertise in General Ledger (FI- GL), Controlling (CO), Accounts Receivable (AR), Accounts Payable (AP), Asset Accounting (AA), Project Systems (PS) Profitability Analysis (PA), New GL, Experience in Financial Month end Activity, Financial Closing Cockpit(Task template, Task list) and Intercompany reconciliation process. Experience with Simple Finance / Central Finance exposure will be given preference Project experience activities to include preparation, synchronization, conversion and post processing, table mapping for HANA, comprehensive knowledge of BP roles and functionality of S4 HANA Finance is preferred. Should have an overview of Deployment option for S4H. Good to have knowledge in Fiori Apps, Fiori Launchpad, Fiori Launchpad Designer configuration & feature and Fiori application types.
... A31: Excise Duty - FI (custom development) | B31: IS3 | C31: =_xlfn.CONCAT(A31,"_",B31) -> Excise Duty - FI (custom development)_IS3 | D31: Independently take up and participate in Business workshops, Design End to End solutions with SAP Should possess natural analytical way of thinking and troubleshooting issues. Good communication and interpersonal skills. Pls look for unique roles as follows : 1. SAP FICO, 2. SAP Treasury Managemant, 3. SAP Cash Management, 4. SAP Central Finance Experience Required : Minimum 6-10 years of experience with 1-2 implementation in SAP ERP and 3 AMS expereince worked with Global customer Experience in SAP cross-functional areas such as SD, MM/PP, PS Strong understanding of all types of order processing models, including B2B, B2C, EDI. Proven experience in project cut-over, successful go-live and client handling during PGLS and alignment with AMS teams will be valued. Strong experience in FI: G/L, AP, AR, Treasury, Assets, Closing and Reporting, CO: CCA, PCA, Internal order, CO-PA, CO-PC Very good experience in Controlling submodules like CO-Product Costing and CO-Profitability Analysis and CO-Profit center Accounting is must. SAP Functional configuration expertise in General Ledger (FI- GL), Controlling (CO), Accounts Receivable (AR), Accounts Payable (AP), Asset Accounting (AA), Project Systems (PS) Profitability Analysis (PA), New GL, Experience in Financial Month end Activity, Financial Closing Cockpit(Task template, Task list) and Intercompany reconciliation process. Experience with Simple Finance / Central Finance exposure will be given preference Project experience activities to include preparation, synchronization, conversion and post processing, table mapping for HANA, comprehensive knowledge of BP roles and functionality of S4 HANA Finance is preferred. Should have an overview of Deployment option for S4H. Good to have knowledge in Fiori Apps, Fiori Launchpad, Fiori Launchpad Designer configuration & feature and Fiori application types.
A33: Recipe Mgmt - PP (custom development) | B33: IS2 | C33: =_xlfn.CONCAT(A33,"_",B33) -> Recipe Mgmt - PP (custom development)_IS2
A34: Recipe Mgmt - PP (custom development) | B34: IS3 | C34: =_xlfn.CONCAT(A34,"_",B34) -> Recipe Mgmt - PP (custom development)_IS3
A36: FSCM (TRM Finance) | B36: IS1 | C36: =_xlfn.CONCAT(A36,"_",B36) -> FSCM (TRM Finance)_IS1 | D36: Should possess natural analytical way of thinking and troubleshooting issues. Good communication and interpersonal skills. Should be able to learn quickly on the new areas / cross functional areas Pls look for unique roles as follows : 1. SAP FICO, 2. SAP Treasury Managemant, 3. SAP Cash Management, 4. SAP Central Finance Experience Required : 2-6 years of experience with 1 implementation in SAP ERP and 1 AMS expereince worked with Global customer Experience in SAP cross-functional areas such as SD, MM/PP, PS Good knowledge in all types of order processing models, including B2B, B2C, EDI. Experience in project cut-over, successful go-live and client handling during PGLS and alignment with AMS teams will be valued. Experience in FI: G/L, AP, AR, Treasury, Assets, Closing and Reporting, CO: CCA, PCA, Internal order, CO-PA, CO-PC Experience in Controlling submodules like CO-Product Costing and CO-Profitability Analysis and CO-Profit center Accounting is must. SAP Functional configuration expertise in General Ledger (FI- GL), Controlling (CO), Accounts Receivable (AR), Accounts Payable (AP), Asset Accounting (AA), Project Systems (PS) Profitability Analysis (PA), New GL, Experience in Financial Month end Activity, Financial Closing Cockpit(Task template, Task list) and Intercompany reconciliation process. Good to have knowledge in Fiori Apps, Fiori Launchpad, Fiori Launchpad Designer configuration & feature and Fiori application types.
A37: FSCM (TRM Finance) | B37: IS2 | C37: =_xlfn.CONCAT(A37,"_",B37) -> FSCM (TRM Finance)_IS2 | D37: Should possess natural analytical way of thinking and troubleshooting issues. Good communication and interpersonal skills. Should be able to learn quickly on the new areas / cross functional areas Pls look for unique roles as follows : 1. SAP FICO, 2. SAP Treasury Managemant, 3. SAP Cash Management, 4. SAP Central Finance Experience Required : 2-6 years of experience with 1 implementation in SAP ERP and 1 AMS expereince worked with Global customer Experience in SAP cross-functional areas such as SD, MM/PP, PS Good knowledge in all types of order processing models, including B2B, B2C, EDI. Experience in project cut-over, successful go-live and client handling during PGLS and alignment with AMS teams will be valued. Experience in FI: G/L, AP, AR, Treasury, Assets, Closing and Reporting, CO: CCA, PCA, Internal order, CO-PA, CO-PC Experience in Controlling submodules like CO-Product Costing and CO-Profitability Analysis and CO-Profit center Accounting is must. SAP Functional configuration expertise in General Ledger (FI- GL), Controlling (CO), Accounts Receivable (AR), Accounts Payable (AP), Asset Accounting (AA), Project Systems (PS) Profitability Analysis (PA), New GL, Experience in Financial Month end Activity, Financial Closing Cockpit(Task template, Task list) and Intercompany reconciliation process. Good to have knowledge in Fiori Apps, Fiori Launchpad, Fiori Launchpad Designer configuration & feature and Fiori application types.
A38: FSCM (TRM Finance) | B38: IS3 | C38: =_xlfn.CONCAT(A38,"_",B38) -> FSCM (TRM Finance)_IS3 | D38: Independently take up and participate in Business workshops, Design End to End solutions with SAP Should possess natural analytical way of thinking and troubleshooting issues. Good communication and interpersonal skills. Pls look for unique roles as follows : 1. SAP FICO, 2. SAP Treasury Managemant, 3. SAP Cash Management, 4. SAP Central Finance Experience Required : Minimum 6-10 years of experience with 1-2 implementation in SAP ERP and 3 AMS expereince worked with Global customer Experience in SAP cross-functional areas such as SD, MM/PP, PS Strong understanding of all types of order processing models, including B2B, B2C, EDI. Proven experience in project cut-over, successful go-live and client handling during PGLS and alignment with AMS teams will be valued. Strong experience in FI: G/L, AP, AR, Treasury, Assets, Closing and Reporting, CO: CCA, PCA, Internal order, CO-PA, CO-PC Very good experience in Controlling submodules like CO-Product Costing and CO-Profitability Analysis and CO-Profit center Accounting is must. SAP Functional configuration expertise in General Ledger (FI- GL), Controlling (CO), Accounts Receivable (AR), Accounts Payable (AP), Asset Accounting (AA), Project Systems (PS) Profitability Analysis (PA), New GL, Experience in Financial Month end Activity, Financial Closing Cockpit(Task template, Task list) and Intercompany reconciliation process. Experience with Simple Finance / Central Finance exposure will be given preference Project experience activities to include preparation, synchronization, conversion and post processing, table mapping for HANA, comprehensive knowledge of BP roles and functionality of S4 HANA Finance is preferred. Should have an overview of Deployment option for S4H. Good to have knowledge in Fiori Apps, Fiori Launchpad, Fiori Launchpad Designer configuration & feature and Fiori application types.
A39: FSCM (TRM Finance) | B39: IS4 | C39: =_xlfn.CONCAT(A39,"_",B39) -> FSCM (TRM Finance)_IS4 | D39: Independently take up and participate in Business workshops, Design End to End solutions with SAP Extensive experience in delivering Agile, DevOps, Activate methology Extensive experience either in leading the SAP AMS / leading the SAP config and development track Should possess natural analytical way of thinking and troubleshooting issues. Exceptional communication and interpersonal skills. Understanding new business strategies, providing recommendations for automated solutions to support new strategies Pls look for unique roles as follows : 1. SAP FICO, 2. SAP Treasury Managemant, 3. SAP Cash Management, 4. SAP Central Finance Experience Required : Minimum 10 years of experience with 2-3 implementation on S/4Hana implementation experience Experience in SAP cross-functional areas such as SD, MM/PP, PS Strong understanding of all types of order processing models, including B2B, B2C, EDI. Proven experience in project cut-over, successful go-live and client handling during PGLS and alignment with AMS teams will be valued. Strong experience in FI: G/L, AP, AR, Treasury, Assets, Closing and Reporting, CO: CCA, PCA, Internal order, CO-PA, CO-PC Very good experience in Controlling submodules like CO-Product Costing and CO-Profitability Analysis and CO-Profit center Accounting is must. SAP Functional configuration expertise in General Ledger (FI- GL), Controlling (CO), Accounts Receivable (AR), Accounts Payable (AP), Asset Accounting (AA), Project Systems (PS) Profitability Analysis (PA), New GL, Experience in Financial Month end Activity, Financial Closing Cockpit(Task template, Task list) and Intercompany reconciliation process. Experience with Simple Finance / Central Finance exposure will be given preference Project experience activities to include preparation, synchronization, conversion and post processing, table mapping for HANA, comprehensive knowledge of BP roles and functionality of S4 HANA Finance is preferred. Should have an overview of Deployment option for S4H. Good to have knowledge in Fiori Apps, Fiori Launchpad, Fiori Launchpad Designer configuration & feature and Fiori application types.
A41: ABAP | B41: IS1 | C41: =_xlfn.CONCAT(A41,"_",B41) -> ABAP_IS1 | D41: 2-6 years of experinece, 1 implementation and 1 support engagement Experience either in worked in SAP AMS / SAP config and development track Pls look for unique roles : 1. SAP ABAP, 2. SAP Workflow, SAP Fiori Good experience within the following SAP toolsets: Middleware, BDOCs, ABAP Mapping, SLD/IR/ID configuration, Web Services, Screen Painter, Classes/Methods, BSPs, ABAP Workbench, WebDynpro for JAVA/ABAP, Workflow, Object Oriented ABAP, Function modules (RFC), SAP Script, Smartforms, Adobe Forms, BPM, User Exits, BADIs, ALV, ALE, EDI, IDOCs, CMOD, Enhancement Spots, BDC/Call Transaction, Logical Database, Data Dictionary, SAP Fiori etc. Good experience in SAP FIORI/UI5 application development, Fiori Design pattern, UI Theme designer, UI principles, FIORI Launchpad configuration, FIORI Gateway Services Java, JavaScript, CSS, HTML5, JQuery development experience preferred Experience in worked multiple modules of SD, MM, PP/QM, WM, APO, FICO, TRM etc. Good communication and interpersonal skills. Should be able to learn quickly on the new areas / cross functional areas
A42: ABAP | B42: IS2 | C42: =_xlfn.CONCAT(A42,"_",B42) -> ABAP_IS2 | D42: 2-6 years of experinece, 1 implementation and 1 support engagement Experience either in worked in SAP AMS / SAP config and development track Pls look for unique roles : 1. SAP ABAP, 2. SAP Workflow, SAP Fiori Good experience within the following SAP toolsets: Middleware, BDOCs, ABAP Mapping, SLD/IR/ID configuration, Web Services, Screen Painter, Classes/Methods, BSPs, ABAP Workbench, WebDynpro for JAVA/ABAP, Workflow, Object Oriented ABAP, Function modules (RFC), SAP Script, Smartforms, Adobe Forms, BPM, User Exits, BADIs, ALV, ALE, EDI, IDOCs, CMOD, Enhancement Spots, BDC/Call Transaction, Logical Database, Data Dictionary, SAP Fiori etc. Good experience in SAP FIORI/UI5 application development, Fiori Design pattern, UI Theme designer, UI principles, FIORI Launchpad configuration, FIORI Gateway Services Java, JavaScript, CSS, HTML5, JQuery development experience preferred Experience in worked multiple modules of SD, MM, PP/QM, WM, APO, FICO, TRM etc. Good communication and interpersonal skills. Should be able to learn quickly on the new areas / cross functional areas
A43: ABAP | B43: IS3 | C43: =_xlfn.CONCAT(A43,"_",B43) -> ABAP_IS3 | D43: Independently take up and participate in Business workshops, Design End to End solutions Extensive experience either in worked in SAP AMS / SAP config and development track Pls look for unique roles : 1. SAP ABAP, 2. SAP Workflow, SAP Fiori Extensive experience within the following SAP toolsets: Middleware, BDOCs, ABAP Mapping, SLD/IR/ID configuration, Web Services, Screen Painter, Classes/Methods, BSPs, ABAP Workbench, WebDynpro for JAVA/ABAP, Workflow, Object Oriented ABAP, Function modules (RFC), SAP Script, Smartforms, Adobe Forms, BPM, User Exits, BADIs, ALV, ALE, EDI, IDOCs, CMOD, Enhancement Spots, BDC/Call Transaction, Logical Database, Data Dictionary, SAP Fiori etc. Extensive experience in SAP FIORI/UI5 application development, Fiori Design pattern, UI Theme designer, UI principles, FIORI Launchpad configuration, FIORI Gateway Services Java, JavaScript, CSS, HTML5, JQuery development experience preferred Experience in worked multiple modules of SD, MM, PP/QM, WM, APO, FICO, TRM etc.
A44: ABAP | B44: IS4 | C44: =_xlfn.CONCAT(A44,"_",B44) -> ABAP_IS4 | D44: Independently take up and participate in Business workshops, Design End to End solutions with SAP Activate, Agile and DevOps methodologies. Extensive experience either in leading the SAP AMS / leading the SAP config and development track Pls look for unique roles : 1. SAP ABAP, 2. SAP Workflow, SAP Fiori Extensive experience within the following SAP toolsets: Middleware, BDOCs, ABAP Mapping, SLD/IR/ID configuration, Web Services, Screen Painter, Classes/Methods, BSPs, ABAP Workbench, WebDynpro for JAVA/ABAP, Workflow, Object Oriented ABAP, Function modules (RFC), SAP Script, Smartforms, Adobe Forms, BPM, User Exits, BADIs, ALV, ALE, EDI, IDOCs, CMOD, Enhancement Spots, BDC/Call Transaction, Logical Database, Data Dictionary, SAP Fiori etc. Extensive experience in SAP FIORI/UI5 application development, Fiori Design pattern, UI Theme designer, UI principles, FIORI Launchpad configuration, FIORI Gateway Services Java, JavaScript, CSS, HTML5, JQuery development experience preferred Experience in worked multiple modules of SD, MM, PP/QM, WM, APO, FICO, TRM etc.
A45: ABAP | B45: IS5 | C45: =_xlfn.CONCAT(A45,"_",B45) -> ABAP_IS5 | D45: Independently take up and participate in Business workshops, Design End to End solutions with SAP Activate, Agile and DevOps methodologies. Extensive experience either in leading the SAP AMS / leading the SAP config and development track Pls look for unique roles : 1. SAP ABAP, 2. SAP Workflow, SAP Fiori Extensive experience within the following SAP toolsets: Middleware, BDOCs, ABAP Mapping, SLD/IR/ID configuration, Web Services, Screen Painter, Classes/Methods, BSPs, ABAP Workbench, WebDynpro for JAVA/ABAP, Workflow, Object Oriented ABAP, Function modules (RFC), SAP Script, Smartforms, Adobe Forms, BPM, User Exits, BADIs, ALV, ALE, EDI, IDOCs, CMOD, Enhancement Spots, BDC/Call Transaction, Logical Database, Data Dictionary, SAP Fiori etc. Extensive experience in SAP FIORI/UI5 application development, Fiori Design pattern, UI Theme designer, UI principles, FIORI Launchpad configuration, FIORI Gateway Services Java, JavaScript, CSS, HTML5, JQuery development experience preferred Experience in worked multiple modules of SD, MM, PP/QM, WM, APO, FICO, TRM etc.
A46: ABAP | B46: IS6 | C46: =_xlfn.CONCAT(A46,"_",B46) -> ABAP_IS6 | D46: Independently take up and participate in Business workshops, Design End to End solutions with SAP Activate, Agile and DevOps methodologies. Extensive experience either in leading the SAP AMS / leading the SAP config and development track Pls look for unique roles : 1. SAP ABAP, 2. SAP Workflow, SAP Fiori Extensive experience within the following SAP toolsets: Middleware, BDOCs, ABAP Mapping, SLD/IR/ID configuration, Web Services, Screen Painter, Classes/Methods, BSPs, ABAP Workbench, WebDynpro for JAVA/ABAP, Workflow, Object Oriented ABAP, Function modules (RFC), SAP Script, Smartforms, Adobe Forms, BPM, User Exits, BADIs, ALV, ALE, EDI, IDOCs, CMOD, Enhancement Spots, BDC/Call Transaction, Logical Database, Data Dictionary, SAP Fiori etc. Extensive experience in SAP FIORI/UI5 application development, Fiori Design pattern, UI Theme designer, UI principles, FIORI Launchpad configuration, FIORI Gateway Services Java, JavaScript, CSS, HTML5, JQuery development experience preferred Experience in worked multiple modules of SD, MM, PP/QM, WM, APO, FICO, TRM etc.
A48: Portal | B48: IS2 | C48: =_xlfn.CONCAT(A48,"_",B48) -> Portal_IS2 | D48: 1-3 years’ experience with SAP implementation and SAP services management, 1 implementation and 1 AMS projects Experience either in worked the SAP AMS / the SAP config and development track Should have working experience on SAP Enterprise Portal Administration and Development. Should be exposed to atleast one of Webydnpro JAVA/ JAVA Portal applications design and development. Good knowledge and understanding of LDAP, UME, SSO, FPN Configurations. Experience in System object creation, transport of portal content, Destination Configurations. Knowledge on UI theme designer and KM Content is added advantage.
A49: Portal | B49: IS3 | C49: =_xlfn.CONCAT(A49,"_",B49) -> Portal_IS3 | D49: At least 8 years’ experience with SAP implementation and SAP services management with large global organisations with large SAP installations across multiple geographies. Extensive experience either in worked the SAP AMS / the SAP config and development track Should have working experience on SAP Enterprise Portal Administration and Development. Should be exposed to atleast one of Webydnpro JAVA/ JAVA Portal applications design and development. Expertise on iViews, Pages, Roles, worksets creation in portal and in user administration activities. Good knowledge and understanding of LDAP, UME, SSO, FPN Configurations. Expertise in System object creation, transport of portal content, Destination Configurations. Knowledge on UI theme designer and KM Content is added advantage.
... A62: FICO+CFIN/SLT | B62: IS4 | C62: =_xlfn.CONCAT(A62,"_",B62) -> FICO+CFIN/SLT_IS4 | D62: Independently take up and participate in Business workshops, Design End to End solutions with SAP Should possess natural analytical way of thinking and troubleshooting issues. Good communication and interpersonal skills. Pls look for unique roles as follows : 1. SAP FICO, 2. SAP Treasury Managemant, 3. SAP Cash Management, 4. SAP Central Finance Experience Required : Minimum 10 years of experience with 1-2 implementation in SAP ERP and 3 AMS expereince worked with Global customer Experience in SAP cross-functional areas such as SD, MM/PP, PS Strong understanding of all types of order processing models, including B2B, B2C, EDI. Proven experience in project cut-over, successful go-live and client handling during PGLS and alignment with AMS teams will be valued. Strong experience in FI: G/L, AP, AR, Treasury, Assets, Closing and Reporting, CO: CCA, PCA, Internal order, CO-PA, CO-PC Very good experience in Controlling submodules like CO-Product Costing and CO-Profitability Analysis and CO-Profit center Accounting is must. SAP Functional configuration expertise in General Ledger (FI- GL), Controlling (CO), Accounts Receivable (AR), Accounts Payable (AP), Asset Accounting (AA), Project Systems (PS) Profitability Analysis (PA), New GL, Experience in Financial Month end Activity, Financial Closing Cockpit(Task template, Task list) and Intercompany reconciliation process. Experience with Simple Finance / Central Finance exposure will be given preference Project experience activities to include preparation, synchronization, conversion and post processing, table mapping for HANA, comprehensive knowledge of BP roles and functionality of S4 HANA Finance is preferred. Should have an overview of Deployment option for S4H. Good to have knowledge in Fiori Apps, Fiori Launchpad, Fiori Launchpad Designer configuration & feature and Fiori application types.
A64: S&V (Fixed asset mgmt) | B64: IS2 | C64: =_xlfn.CONCAT(A64,"_",B64) -> S&V (Fixed asset mgmt)_IS2
A65: S&V (Fixed asset mgmt) | B65: IS3 | C65: =_xlfn.CONCAT(A65,"_",B65) -> S&V (Fixed asset mgmt)_IS3
A67: SAP Basis | B67: IS1 | C67: =_xlfn.CONCAT(A67,"_",B67) -> SAP Basis_IS1 | D67: Good communication and interpersonal skills. Should be able to learn quickly on the new areas / cross functional areas 2-6 years’ experience with SAP implementation and SAP services management, 1 implementaiton and 1 AMS experinece experience either worked in the SAP AMS / leading the SAP config and development track Essential Functions of the Job: Assist with the configuration and maintenance of High Availability and Disaster Recovery SAP solutions. Desired Knowledge and Skills Requirements: Knowledge of SAP software and MS SQL and HANA databases, as well as working experience of key business applications including SAP ECC, BWoH, BOBJ, Cloud based solutions, PI/PO, SRM, SolMan, Fiori. Experience working with SAP installations, upgrades (SAP version, EHP, SPS, Kernel, SUM), maintenance, monitoring, troubleshooting of issues and tuning and optimization. Good knowledge on OS Windows/Linux administration, VMware virtualization, NAS/SAN storage, failover clustering, SAN replication, and other high availability technologies Experience working with middleware, integration and web technologies for SAP solutions. Experience working with Cloud solutions for SAP (installation, configuration, migration, testing, support). Receive direction as the Basis team lead on strategy and operational support on integrated SAP systems and infrastructure. Able to act independently, seeking consultation guidance and advice as appropriate Experience in updates of Solution Manager, SLD and XI content as required.
A68: SAP Basis | B68: IS2 | C68: =_xlfn.CONCAT(A68,"_",B68) -> SAP Basis_IS2 | D68: Good communication and interpersonal skills. Should be able to learn quickly on the new areas / cross functional areas 2-6 years’ experience with SAP implementation and SAP services management, 1 implementaiton and 1 AMS experinece experience either worked in the SAP AMS / leading the SAP config and development track Essential Functions of the Job: Assist with the configuration and maintenance of High Availability and Disaster Recovery SAP solutions. Desired Knowledge and Skills Requirements: Knowledge of SAP software and MS SQL and HANA databases, as well as working experience of key business applications including SAP ECC, BWoH, BOBJ, Cloud based solutions, PI/PO, SRM, SolMan, Fiori. Experience working with SAP installations, upgrades (SAP version, EHP, SPS, Kernel, SUM), maintenance, monitoring, troubleshooting of issues and tuning and optimization. Good knowledge on OS Windows/Linux administration, VMware virtualization, NAS/SAN storage, failover clustering, SAN replication, and other high availability technologies Experience working with middleware, integration and web technologies for SAP solutions. Experience working with Cloud solutions for SAP (installation, configuration, migration, testing, support). Receive direction as the Basis team lead on strategy and operational support on integrated SAP systems and infrastructure. Able to act independently, seeking consultation guidance and advice as appropriate Experience in updates of Solution Manager, SLD and XI content as required.
A69: SAP Basis | B69: IS3 | C69: =_xlfn.CONCAT(A69,"_",B69) -> SAP Basis_IS3 | D69: At least 6 years’ experience with SAP implementation and SAP services management with large global organisations with large SAP installations across multiple geographies. Extensive experience in delivering Agile, DevOps, Activate methology Extensive experience either in worked the SAP AMS / worked the SAP config and development track ssential Functions of the Job: Architect and implement day-to-day SAP basis administration activities in a complex multi-tier SAP landscape. Ensure SAP based systems operate reliably and efficiently in a secure environment. Ensure the adherence of standards and SAP best practices. Be accountable for the support and proactive monitoring of the core SAP applications including installation, performance, break fixes and change requests per business requirements Research complex application/System integration issues with functional teams; examine integration between various systems (SAP and non-SAP) for inconsistencies. Assist with the configuration and maintenance of High Availability and Disaster Recovery SAP solutions. Desired Knowledge and Skills Requirements: Thorough knowledge of SAP software and MS SQL and HANA databases, as well as working experience of key business applications including SAP ECC, BWoH, BOBJ, Cloud based solutions, PI/PO, SRM, SolMan, Fiori. Experience working with SAP installations, upgrades (SAP version, EHP, SPS, Kernel, SUM), maintenance, monitoring, troubleshooting of issues and tuning and optimization. Good knowledge on OS Windows/Linux administration, VMware virtualization, NAS/SAN storage, failover clustering, SAN replication, and other high availability technologies Experience working with middleware, integration and web technologies for SAP solutions. Experience working with Cloud solutions for SAP (installation, configuration, migration, testing, support). Receive direction as the Basis team lead on strategy and operational support on integrated SAP systems and infrastructure. Able to act independently, seeking consultation guidance and advice as appropriate Experience in updates of Solution Manager, SLD and XI content as required.
A70: SAP Basis | B70: IS4 | C70: =_xlfn.CONCAT(A70,"_",B70) -> SAP Basis_IS4 | D70: At least 8 years’ experience with SAP implementation and SAP services management with large global organisations with large SAP installations across multiple geographies. Extensive experience in delivering Agile, DevOps, Activate methology Extensive experience either in leading the SAP AMS / leading the SAP config and development track ssential Functions of the Job: Architect and implement day-to-day SAP basis administration activities in a complex multi-tier SAP landscape. Ensure SAP based systems operate reliably and efficiently in a secure environment. Ensure the adherence of standards and SAP best practices. Be accountable for the support and proactive monitoring of the core SAP applications including installation, performance, break fixes and change requests per business requirements Research complex application/System integration issues with functional teams; examine integration between various systems (SAP and non-SAP) for inconsistencies. Assist with the configuration and maintenance of High Availability and Disaster Recovery SAP solutions. Desired Knowledge and Skills Requirements: Thorough knowledge of SAP software and MS SQL and HANA databases, as well as working experience of key business applications including SAP ECC, BWoH, BOBJ, Cloud based solutions, PI/PO, SRM, SolMan, Fiori. Experience working with SAP installations, upgrades (SAP version, EHP, SPS, Kernel, SUM), maintenance, monitoring, troubleshooting of issues and tuning and optimization. Good knowledge on OS Windows/Linux administration, VMware virtualization, NAS/SAN storage, failover clustering, SAN replication, and other high availability technologies Experience working with middleware, integration and web technologies for SAP solutions. Experience working with Cloud solutions for SAP (installation, configuration, migration, testing, support). Receive direction as the Basis team lead on strategy and operational support on integrated SAP systems and infrastructure. Able to act independently, seeking consultation guidance and advice as appropriate Experience in updates of Solution Manager, SLD and XI content as required.
A71: SAP Basis | B71: IS5 | C71: =_xlfn.CONCAT(A71,"_",B71) -> SAP Basis_IS5 | D71: At least 10 years’ experience with SAP implementation and SAP services management with large global organisations with large SAP installations across multiple geographies. Extensive experience in delivering Agile, DevOps, Activate methology Extensive experience either in leading the SAP AMS / leading the SAP config and development track ssential Functions of the Job: Architect and implement day-to-day SAP basis administration activities in a complex multi-tier SAP landscape. Ensure SAP based systems operate reliably and efficiently in a secure environment. Ensure the adherence of standards and SAP best practices. Be accountable for the support and proactive monitoring of the core SAP applications including installation, performance, break fixes and change requests per business requirements Research complex application/System integration issues with functional teams; examine integration between various systems (SAP and non-SAP) for inconsistencies. Assist with the configuration and maintenance of High Availability and Disaster Recovery SAP solutions. Desired Knowledge and Skills Requirements: Thorough knowledge of SAP software and MS SQL and HANA databases, as well as working experience of key business applications including SAP ECC, BWoH, BOBJ, Cloud based solutions, PI/PO, SRM, SolMan, Fiori. Experience working with SAP installations, upgrades (SAP version, EHP, SPS, Kernel, SUM), maintenance, monitoring, troubleshooting of issues and tuning and optimization. Good knowledge on OS Windows/Linux administration, VMware virtualization, NAS/SAN storage, failover clustering, SAN replication, and other high availability technologies Experience working with middleware, integration and web technologies for SAP solutions. Experience working with Cloud solutions for SAP (installation, configuration, migration, testing, support). Receive direction as the Basis team lead on strategy and operational support on integrated SAP systems and infrastructure. Able to act independently, seeking consultation guidance and advice as appropriate Experience in updates of Solution Manager, SLD and XI content as required.
A73: APO (DP, SNP, TLB) + SNC | B73: IS1 | C73: =_xlfn.CONCAT(A73,"_",B73) -> APO (DP, SNP, TLB) + SNC_IS1 | D73: 2-5 years’ experience with SAP implementation and SAP services management with large global organisations with large SAP installations across multiple geographies. Experience either worked in the SAP AMS / the SAP config and development track, 1 implementation and 1 AMS experinence Essential Functions of the Job Looking for unique roles for the JD 1. SAP DP, 2. SAP SNP, SAP PPDS, SAP SNC Experience in one or more modules : SCM solution – Demand Planning (APO DP), Distribution Requirements Planning and Manufacturing Planning (APO SNP and APO PP DS), Supplier Network Colloboration (SNC) influence skills to drive business solutions. understanding of APO and interdependency of different processes within APO Experience should be in End-to-end Implementation and AMS knowledge on either coupe of the modules - DP, SNP, CIF, PPDS, SNC, TLB and and SAP APO-ECC integration Good interpersonal skills and willing for learning and cross skilling
A74: APO (DP, SNP, TLB) + SNC | B74: IS2 | C74: =_xlfn.CONCAT(A74,"_",B74) -> APO (DP, SNP, TLB) + SNC_IS2 | D74: 2-5 years’ experience with SAP implementation and SAP services management with large global organisations with large SAP installations across multiple geographies. Experience either worked in the SAP AMS / the SAP config and development track, 1 implementation and 1 AMS experinence Essential Functions of the Job Looking for unique roles for the JD 1. SAP DP, 2. SAP SNP, SAP PPDS, SAP SNC Experience in one or more modules : SCM solution – Demand Planning (APO DP), Distribution Requirements Planning and Manufacturing Planning (APO SNP and APO PP DS), Supplier Network Colloboration (SNC) influence skills to drive business solutions. understanding of APO and interdependency of different processes within APO Experience should be in End-to-end Implementation and AMS knowledge on either coupe of the modules - DP, SNP, CIF, PPDS, SNC, TLB and and SAP APO-ECC integration Good interpersonal skills and willing for learning and cross skilling
A75: APO (DP, SNP, TLB) + SNC | B75: IS3 | C75: =_xlfn.CONCAT(A75,"_",B75) -> APO (DP, SNP, TLB) + SNC_IS3 | D75: At least 6 years’ experience with SAP implementation and SAP services management with large global organisations with large SAP installations across multiple geographies. Extensive experience either worked in the SAP AMS / the SAP config and development track ssential Functions of the Job Looking for unique roles for the JD 1. SAP DP, 2. SAP SNP, SAP PPDS, SAP SNC Extentive experience in one or more modules : SCM solution – Demand Planning (APO DP), Distribution Requirements Planning and Manufacturing Planning (APO SNP and APO PP DS), Supplier Network Colloboration (SNC) influence skills to drive business solutions. Must have deep understanding of APO and interdependency of different processes within APO Extensive experience should be in End-to-end Implementation, Support, upgrade, optimization and various areas with implementation of Sub-modules like DP, SNP, CIF, PPDS, SNC, TLB and and SAP APO-ECC integration
A76: APO (DP, SNP, TLB) + SNC | B76: IS4 | C76: =_xlfn.CONCAT(A76,"_",B76) -> APO (DP, SNP, TLB) + SNC_IS4 | D76: At least 8 years’ experience with SAP implementation and SAP services management with large global organisations with large SAP installations across multiple geographies. Extensive experience in delivering Agile, DevOps, Activate methology Extensive experience either in leading the SAP AMS / leading the SAP config and development track ssential Functions of the Job Looking for unique roles for the JD 1. SAP DP, 2. SAP SNP, SAP PPDS, SAP SNC Extentive experience in one or more modules : SCM solution – Demand Planning (APO DP), Distribution Requirements Planning and Manufacturing Planning (APO SNP and APO PP DS), Supplier Network Colloboration (SNC) influence skills to drive business solutions. Must have deep understanding of APO and interdependency of different processes within APO Extensive experience should be in End-to-end Implementation, Support, upgrade, optimization and various areas with implementation of Sub-modules like DP, SNP, CIF, PPDS, SNC, TLB and and SAP APO-ECC integration
A77: APO (DP, SNP, TLB) + SNC | B77: IS5 | C77: =_xlfn.CONCAT(A77,"_",B77) -> APO (DP, SNP, TLB) + SNC_IS5 | D77: At least 10 years’ experience with SAP implementation and SAP services management with large global organisations with large SAP installations across multiple geographies. Extensive experience in delivering Agile, DevOps, Activate methology Extensive experience either in leading the SAP AMS / leading the SAP config and development track ssential Functions of the Job Looking for unique roles for the JD 1. SAP DP, 2. SAP SNP, SAP PPDS, SAP SNC Extentive experience in one or more modules : SCM solution – Demand Planning (APO DP), Distribution Requirements Planning and Manufacturing Planning (APO SNP and APO PP DS), Supplier Network Colloboration (SNC) influence skills to drive business solutions. Must have deep understanding of APO and interdependency of different processes within APO Extensive experience should be in End-to-end Implementation, Support, upgrade, optimization and various areas with implementation of Sub-modules like DP, SNP, CIF, PPDS, SNC, TLB and and SAP APO-ECC integration
A79: Vistex (SD,LE) - Non TCS - Canada, Niche (ABAP, SD, FI) | B79: IS2 | C79: =_xlfn.CONCAT(A79,"_",B79) -> Vistex (SD,LE) - Non TCS - Canada, Niche (ABAP, SD, FI)_IS2 | D79: Experence of around 1-4 years with excellent communication skills The candidate must have strong design and implementation knowledge of either SAP SD or MM mainly covering Pricing, OTC process / Purchasing process, Master data, Enterprise elements and SD / MM - Finance integration. Experience in 1-2 full lifecycle software implementations and 1 AMS implementation experience Collaborative and consultative work style Ability to link business processes with products/solutions
A80: Vistex (SD,LE) - Non TCS - Canada, Niche (ABAP, SD, FI) | B80: IS3 | C80: =_xlfn.CONCAT(A80,"_",B80) -> Vistex (SD,LE) - Non TCS - Canada, Niche (ABAP, SD, FI)_IS3 | D80: Independently take up and participate in Business workshops, Design End to End solutions . Experence of around 6+ years with excellent communication skills Experience in managing large teams and customer facing rolls Understand and work with different teams to provide solution roadmap to clients The candidate must have strong design and implementation knowledge of either SAP SD or MM mainly covering Pricing, OTC process / Purchasing process, Master data, Enterprise elements and SD / MM - Finance integration. Experience in 1-2 full lifecycle software implementations and 2 AMS implementation experience Collaborative and consultative work style Ability to link business processes with products/solutions
A82: CPS | B82: IS2 | C82: =_xlfn.CONCAT(A82,"_",B82) -> CPS_IS2
A83: CPS | B83: IS3 | C83: =_xlfn.CONCAT(A83,"_",B83) -> CPS_IS3
A84: CPS | B84: IS4 | C84: =_xlfn.CONCAT(A84,"_",B84) -> CPS_IS4
A86: PLM (MDG and ECC) | B86: IS2 | C86: =_xlfn.CONCAT(A86,"_",B86) -> PLM (MDG and ECC)_IS2 | D86: 2 to 6 years’ experience with SAP implementation and SAP services management, 1 implementation and 1 AMS experience Experience in assessment and gap analysis of MDM projects, test and validate all releases and regression Support business users with MDG data (customer, pricing, vendor, finance and accounting, APO, HR, workflow processes) Manages the analysis and execution of new master data setup or data changes Effectively coordinate with internal team, partners and Customer's data governanace COE to manage the day-to-day maintenance requirement Experience in automate access control the business functions can see and act upon the data in accordance with their job function Proactively seeks, analyses, adminsters and communicates actionable data to the customer around data management
A87: PLM (MDG and ECC) | B87: IS3 | C87: =_xlfn.CONCAT(A87,"_",B87) -> PLM (MDG and ECC)_IS3 | D87: At least 8 years’ experience with SAP implementation and SAP services management with large global organisations with large SAP installations across multiple geographies. Extensive experience in delivering Agile, DevOps, Activate methology Should have Delivery management experience of 8+ years in SAP implementation, Rollout, Managed Services for manufacturing/CPG domain Lead the assessment and gap analysis of MDM projects, test and validate all releases and regression Support business users with MDG data (customer, pricing, vendor, finance and accounting, APO, HR, workflow processes) Manages the analysis and execution of new master data setup or data changes Effectively coordinate with internal team, partners and Customer's data governanace COE to manage the day-to-day maintenance requirement Automates access control the business functions can see and act upon the data in accordance with their job function Proactively seeks, analyses, adminsters and communicates actionable data to the customer around data management
A88: PLM (MDG and ECC) | B88: IS4 | C88: =_xlfn.CONCAT(A88,"_",B88) -> PLM (MDG and ECC)_IS4 | D88: At least 15 years’ experience with SAP implementation and SAP services management with large global organisations with large SAP installations across multiple geographies. Have onsite delivery experience around 6+ yeaear preferably in APAC and Europe Extensive experience in delivering Agile, DevOps, Activate methology Should have Delivery management experience of 15+ years in SAP implementation, Rollout, Managed Services for manufacturing/CPG domain Lead the assessment and gap analysis of MDM projects, test and validate all releases and regression Support business users with MDG data (customer, pricing, vendor, finance and accounting, APO, HR, workflow processes) Manages the analysis and execution of new master data setup or data changes Effectively coordinate with internal team, partners and Customer's data governanace COE to manage the day-to-day maintenance requirement Automates access control the business functions can see and act upon the data in accordance with their job function Proactively seeks, analyses, adminsters and communicates actionable data to the customer around data management
A90: SAP Consultant | B90: IS6 | C90: =_xlfn.CONCAT(A90,"_",B90) -> SAP Consultant_IS6

Sheet Integration
A1: Skill | B1: Grade | C1: JD Ref ID | D1: JD | E1: Panel
A2: SAP PO/PI/CPI | B2: IS1 | C2: =_xlfn.CONCAT(A2,"_",B2) -> SAP PO/PI/CPI_IS1 | D2: 1-2 yrs of experience in implement and deploy SAP Cloud Integration Suite solutions (CPI), SAP PO, SAP PI to achieve defined business goals Maintain skills in SAP applications process design and configuration Work as part of small teams and/or work efforts (if in an individual contributor role) to deliver integration solutions to customers. Production Support of integration processes as needed Technical configuration for domain areas Escalation point for solution design or troubleshooting with outside service partners Supporting and implementing technical integrations with a variety of global 3rd party applications. Must be a team player to collaboratively and effectively deliver high quality work product and communicate with others on multi-disciplinary teams. Responsible for troubleshooting technical problems. Map the business process to SAP Technologies-CPI, BOOMI, SAP Fiori, SAP UI5,etc.
A3: SAP PO/PI/CPI | B3: IS2 | C3: =_xlfn.CONCAT(A3,"_",B3) -> SAP PO/PI/CPI_IS2 | D3: 3-5 yrs of experience in Design, implement and deploy SAP Cloud Integration Suite solutions (CPI), SAP PO, SAP PI to achieve defined business goals Maintain skills in SAP applications process design and configuration SAP application design, development, integration, testing, deployment and technical architecture Work as part of small teams and/or work efforts (if in an individual contributor role) to deliver integration solutions to customers. Implement or deploy capabilities as required: End-to-End process design, testing strategy, cutover plans, training, etc. Production Support of integration processes as needed Technical configuration for domain areas Escalation point for solution design or troubleshooting with outside service partners Supporting and implementing technical integrations with a variety of global 3rd party applications. Understand end-to-end Business Processes Must be a team player to collaboratively and effectively deliver high quality work product and communicate with others on multi-disciplinary teams. Responsible for successful end to end delivery. Responsible for troubleshooting technical problems. Map the business process to SAP Technologies-CPI, BOOMI, SAP Fiori, SAP UI5,etc.
A4: SAP PO/PI/CPI | B4: IS3 | C4: =_xlfn.CONCAT(A4,"_",B4) -> SAP PO/PI/CPI_IS3 | D4: 5-7 yrs of experience in Design, implement and deploy SAP Cloud Integration Suite solutions (CPI), SAP PO, SAP PI to achieve defined business goals Maintain skills in SAP applications process design and configuration SAP application design, development, integration, testing, deployment and technical architecture Work as part of small teams and/or work efforts (if in an individual contributor role) to deliver integration solutions to customers. Implement or deploy capabilities as required: End-to-End process design, testing strategy, cutover plans, training, etc. Production Support of integration processes as needed Technical configuration for domain areas Escalation point for solution design or troubleshooting with outside service partners Supporting and implementing technical integrations with a variety of global 3rd party applications. Understand end-to-end Business Processes Must be a team player to collaboratively and effectively deliver high quality work product and communicate with others on multi-disciplinary teams. Responsible for successful end to end delivery. Responsible for troubleshooting technical problems. Map the business process to SAP Technologies-CPI, BOOMI, SAP Fiori, SAP UI5,etc.
A5: SAP PO/PI/CPI | B5: IS4 | C5: =_xlfn.CONCAT(A5,"_",B5) -> SAP PO/PI/CPI_IS4 | D5: 7+ years of experince in SAP integration including SAP PO, PI and CPI Analyze integration requirements, design and implement complex, state-of-the-art end-to-end integration scenarios across multiple technologies and multiple modules. Define integration architectures and API strategies. Interface design and implementation based on SAP Cloud Platform Integration Suite and SAP Process Orchestration. Integration of cloud solutions and platforms (SAP, Salesforce, Azure, AWS), IoT services and external business partners. Evaluate new SAP technologies and supporting building know-how in these areas, which are integrated into cbs processes. Technical integration consulting and development as part of global SAP ECC, S/4HANA or C/4HANA implementation projects. Be responsible for cbs projects and customers in the technology area as well as engage in pre-sales support in all kinds of SAP technology topics. Act as a technical team lead for the requested deliverables which includes adhering to the timeline, effort and assuring quality. Collaboration with the onsite team. Coach colleagues in functional, technical, and methodic topics. Sharing knowledge and experience with the colleagues. Contribute to cbs best practices and methodologies. Desire for a dynamic and prestigious work environment.
A6: SAP PO/PI/CPI | B6: IS5 | C6: =_xlfn.CONCAT(A6,"_",B6) -> SAP PO/PI/CPI_IS5 | D6: 10+ years of experince in SAP integration including SAP PO, PI and CPI Analyze integration requirements, design and implement complex, state-of-the-art end-to-end integration scenarios across multiple technologies and multiple modules. Define integration architectures and API strategies. Interface design and implementation based on SAP Cloud Platform Integration Suite and SAP Process Orchestration. Integration of cloud solutions and platforms (SAP, Salesforce, Azure, AWS), IoT services and external business partners. Evaluate new SAP technologies and supporting building know-how in these areas, which are integrated into cbs processes. Technical integration consulting and development as part of global SAP ECC, S/4HANA or C/4HANA implementation projects. Be responsible for cbs projects and customers in the technology area as well as engage in pre-sales support in all kinds of SAP technology topics. Act as a technical team lead for the requested deliverables which includes adhering to the timeline, effort and assuring quality. Collaboration with the onsite team. Coach colleagues in functional, technical, and methodic topics. Sharing knowledge and experience with the colleagues. Contribute to cbs best practices and methodologies.
A7: SAP PO/PI/CPI | B7: I5+ | C7: =_xlfn.CONCAT(A7,"_",B7) -> SAP PO/PI/CPI_I5+ | D7: 13+ years of experince in SAP integration including SAP PO, PI and CPI Analyze integration requirements, design and implement complex, state-of-the-art end-to-end integration scenarios across multiple technologies and multiple modules. Define integration architectures and API strategies. Interface design and implementation based on SAP Cloud Platform Integration Suite and SAP Process Orchestration. Integration of cloud solutions and platforms (SAP, Salesforce, Azure, AWS), IoT services and external business partners. Evaluate new SAP technologies and supporting building know-how in these areas, which are integrated into cbs processes. Technical integration consulting and development as part of global SAP ECC, S/4HANA or C/4HANA implementation projects. Be responsible for cbs projects and customers in the technology area as well as engage in pre-sales support in all kinds of SAP technology topics. Act as a technical team lead for the requested deliverables which includes adhering to the timeline, effort and assuring quality. Collaboration with the onsite team. Coach colleagues in functional, technical, and methodic topics. Sharing knowledge and experience with the colleagues. Contribute to cbs best practices and methodologies.
C8: =_xlfn.CONCAT(A8,"_",B8) -> _
A9: Mulesoft | B9: IS1 | C9: =_xlfn.CONCAT(A9,"_",B9) -> Mulesoft_IS1 | D9: Required Skills: Responsible for building integration solutions on the MuleSoft Anypoint Platform with design of specifications, design and development of APIs meeting, deployment, testing and Support. 0- 2 yrs of Experience required in Mulesoft Development. Experience working directly with technical and business teams. Knowledge of SDLC, IT governance and operations. Experience in packaging and deploying MuleSoft applications. Experience working with CI/CD tools like GitHub, Maven, Azure DevOps etc. Experience with messaging platforms Anypoint MQ,IBM MQ etc. Experience working with Mule Connectors ( Standard & Custom). Bachelors degree required. Good verbal and written communication skills are essential. Strong critical thinking and problem-solving skills. Experience working with overseas teams.
A10: Mulesoft | B10: IS2 | C10: =_xlfn.CONCAT(A10,"_",B10) -> Mulesoft_IS2 | D10: Required Skills: Responsible for building integration solutions on the MuleSoft Anypoint Platform with design of specifications, design and development of APIs meeting, deployment, testing and Support. 3- 5 yrs of Experience required in Mulesoft Development. Experience working directly with technical and business teams. Knowledge of SDLC, IT governance and operations. Experience in packaging and deploying MuleSoft applications. Experience working with CI/CD tools like GitHub, Maven, Azure DevOps etc. Experience with messaging platforms Anypoint MQ,IBM MQ etc. Experience working with Mule Connectors ( Standard & Custom). Bachelors degree required. Good verbal and written communication skills are essential. Strong critical thinking and problem-solving skills. Experience working with overseas teams. MuleSoft developer certified shall be preferred
A11: Mulesoft | B11: IS3 | C11: =_xlfn.CONCAT(A11,"_",B11) -> Mulesoft_IS3 | D11: 5+ years of software development experience with extensive integration experience in MuleSoft 4+ years of development experience using MuleSoft suite of products - Any point Platform, Design Center, Connectors, Exchange, Runtime manager and API Management tools. 2+ years of application development experience. Strong technical knowledge and work experience in implementing integrations with Web services / SOAP / RESTful/gRPC/ Graphql / file based integration patterns and use of different Mule connectors (Any point MQ, Kafka, Azure Event Hub, File, Http/Https, Siebel, ServiceNow, SAP SuccessFactors, Salesforce, Oracle EBS Connector etc.) Experience in developing Microservices architecture-based API, Event Driven and Batch style integration patterns Experience in Java 1.8, Data Weave, JSON, Open API and RAML is required in a cloud or hybrid architecture platfor Business process knowledge and work experience with ERP / Cloud systems within Sales, Marketing, Finance and CRM domains. Experience with DevOps culture and CI/CD tools Participate in proof-of-concept to demonstrate feasibility. Experience of security models, encryption, routing, transformations, error handling, logging, and testing frameworks. Working experience on Agile, Azure Devops and SDLC processes. Good communication, analytical skills.
A12: Mulesoft | B12: IS4 | C12: =_xlfn.CONCAT(A12,"_",B12) -> Mulesoft_IS4 | D12: 7+ years of Overall experience and Experience in architecture, design and implementation of MuleSoft integration and integration experience along with Java based solutions (refer mandatory skills) Candidate should have 1+ years of Architecture design and consulting skills Extensive experience in API's / Web services / SOA development Extensive experience with successful implementations of highly scalable and highly available systems Experience with agile/DevOps development processes Skills Required Expertise in Muelsoft, Expertise in Java, Web services, APIs, SOA and any RDBMS Messaging - JMS APIs, ActiveMQ etc Development tools (Maven, Ant, Jira, Eclipse) Any source versioning control tools expertise Good knowledge on OOPS concepts and design/integration patterns
A13: Mulesoft | B13: IS5 | C13: =_xlfn.CONCAT(A13,"_",B13) -> Mulesoft_IS5 | D13: 10-12 years of experience as an Architect for developing API, ESB, Middleware tools based messaging or EDI or customer integration. Application developed involves communication with both .Net, Java, or Microservices based new or existing legacy platforms Excellent knowledge and hands-on experience with multiple platforms and related technologies: MuleSoft, any Opensource ESB, .Net WebAPI, Java Messaging Service, Apache Kafka, IBM CP4I, Rabbit MQ. Experience with common architectures like Hub-Spoke, Federated ESB, Open API, Queues, Streaming Architecture Knowledge of common software engineering practices Requirements Engineering, Design Patterns, Code Analysis, Performance, DevOps (CI/CD) and architecture modelling practices (UML, Swagger, etc.) Architect the solution for web and hybrid enterprise applications for several platforms (Mobile, Web, B2C/ B2B, Data systems) Know the best practices and risks in terms of security. Always keen to learn new things, share your knowledge, embrace change and learn from past experiences. Integrate with other application developed in Cloud or on-premise Collaborate with Product Team and Application team Review code for well-designed components and testable code Integrate software components into a fully functional software system Troubleshoot, debug and upgrade existing integration Comply with project plans Comply to industry best practices and standards Should possess excellent time management skills
C14: =_xlfn.CONCAT(A14,"_",B14) -> _
A15: Talend | B15: IS1 | C15: =_xlfn.CONCAT(A15,"_",B15) -> Talend_IS1 | D15: 1-2 yrs of Talend developer experience , ETL development , RDBMS , SQL , TAC, TMC. • Knowledge and hands-on experience with ETL development • Hands on experience on implementing different loading strategies like SCD1 and SCD2, Table/ partition refresh, insert update, Swap Patriation using Talend. • Experience in Consuming and writing data from and to Flat files, RDMBS systems, MPPS, Jason and XML using Talend • Experience on RDBMS systems and concepts • Expertise in writing and complex SQL queries and developing Database components including creating views, stored procedures, triggers etc. • Create test cases and perform unit testing of ETL Jobs using Talend. • Hands on experience on ETL jobs orchestration using Talend. • Hands on experience on creating Triggers on TAC server for Scheduling the Talend jobs • Experience on creating batch level processing, parallel process using Talend. • Analytical mind with a problem-solving and debugging skills. • Excellent Communication Skills • Awareness of Replication, Synchronization and Disaster Management techniques • Awareness of Data Quality Management
A16: Talend | B16: IS2 | C16: =_xlfn.CONCAT(A16,"_",B16) -> Talend_IS2 | D16: 3-5 yrs of Talend developer experience , ETL development , RDBMS , SQL , TAC, TMC. • Knowledge and hands-on experience with ETL development • Hands on experience on implementing different loading strategies like SCD1 and SCD2, Table/ partition refresh, insert update, Swap Patriation using Talend. • Experience in Consuming and writing data from and to Flat files, RDMBS systems, MPPS, Jason and XML using Talend • Experience on RDBMS systems and concepts • Expertise in writing and complex SQL queries and developing Database components including creating views, stored procedures, triggers etc. • Create test cases and perform unit testing of ETL Jobs using Talend. • Hands on experience on ETL jobs orchestration using Talend. • Hands on experience on creating Triggers on TAC server for Scheduling the Talend jobs
A17: Talend | B17: IS3 | C17: =_xlfn.CONCAT(A17,"_",B17) -> Talend_IS3 | D17: 5-7 yrs of experience of ETL and ELT tool Talend - Good knowledge of ETL scripting languages like custom DSL, Java or JavaScript - Very good knowledge of JSON, XML and Transformations like XSLT - Good experience with either Mysql or sql or oracle - Good knowledge of Query Optimization - Good knowledge like Python Pandas, Dask, NumPy etc. - Exposure to Bit Data technologies and Analytics platforms like Hadoop, Spark, Shark, Impala, R, Weka etc. - Good knowledge of integrating the ETL tool through triggers RESTful APIs, Workflow engines - Superb interpersonal, communication, and collaboration skills. - Great organizational and time management skills. - Availability to resolve issues outside of business hours.
A18: Talend | B18: IS4 | C18: =_xlfn.CONCAT(A18,"_",B18) -> Talend_IS4 | D18: Should have 10+ years of experience on multiple Talend products (DI, ESB) with having a good understanding of Talend roadmap. Experience with performing key architecture and design in the area of Talend DI and ESB. Experience with managing a community of practice (especially Talend) consisting of ETL developer responsible for data movement and transformation across various data assets in DaaS (Data-as-a-service) using multiple ETL tools including Talend, IBM DataStage, Informatica etc is strongly preferred. Experience with establishing the roadmap for the ETL practice for DaaS and providing leadership with an on-going focus on reusability, scalability and innovation within the community of practice. Prior experience with identifying and recommending opportunities to enhance productivity, effectiveness and operational efficiency of the business unit and/or team. Experience with API/first architecture design, distributed systems (e.g., microservices, Virtualization) and cloud infrastructure for large scale data warehouse, data lakes, data fabric Extensive hands-on experience with building tools/accelerators for migrating from one ETL tool to other including migrating to Snowflake etc. Should be able to manage stakeholders at various levels independently and understand the client’s IT state and business. He / She should be able to build a team and guide team members towards quality delivery and focused up skilling. Experience in solutioning / Architecting Talend project including infrastructure sizing etc Should have worked in min 4-5 Talend + SQL projects Good knowledge in Database and strong SQL knowledge Should be able to transfer Business Requirement to Technical Document Should be able to do Estimation of effort based on the requirement Hands on experience Talend DI with database and file handling Knowledge of SDLC / Agile methodologies and tools
C19: =_xlfn.CONCAT(A19,"_",B19) -> _
A20: EDI | B20: IS1 | C20: =_xlfn.CONCAT(A20,"_",B20) -> EDI_IS1
A21: EDI | B21: IS2 | C21: =_xlfn.CONCAT(A21,"_",B21) -> EDI_IS2
A22: EDI | B22: IS3 | C22: =_xlfn.CONCAT(A22,"_",B22) -> EDI_IS3
C23: =_xlfn.CONCAT(A23,"_",B23) -> _
A24: Axway | B24: IS1 | C24: =_xlfn.CONCAT(A24,"_",B24) -> Axway_IS1
A25: Axway | B25: IS2 | C25: =_xlfn.CONCAT(A25,"_",B25) -> Axway_IS2
A26: Axway | B26: IS3 | C26: =_xlfn.CONCAT(A26,"_",B26) -> Axway_IS3
A27: Axway | B27: IS4 | C27: =_xlfn.CONCAT(A27,"_",B27) -> Axway_IS4
C28: =_xlfn.CONCAT(A28,"_",B28) -> _
A29: ADO | B29: IS2 | C29: =_xlfn.CONCAT(A29,"_",B29) -> ADO_IS2
C30: =_xlfn.CONCAT(A30,"_",B30) -> _

Sheet D2CCRM
A1: Skill | B1: Grade | C1: JD Ref ID | D1: JD | E1: Panel
A2: Scrum Master | B2: IS4 | C2: =_xlfn.CONCAT(A2,"_",B2) -> Scrum Master_IS4 | D2: Relevant Experience 3-5 Years in the Role- Agile Process, Scrum master Overall Experience 8-10 Years - Agile management in all areas of SDLC Experience Details • Should have worked as Scrum Master or RTE or Product Owner for on at least two or more implementations for SFDC projects • Expertise in Agile and Lean ways of working at project/ enterprise level. . • In depth knowledge of Scrum, Kanban and Scaling agile models. • Experience in training individuals and teams in agile principles and practices. . • Provide hands on coaching to 2-4 Agile teams simultaneously with in-depth guidance on agile roles, rituals, and artifacts. • Continuously measure and report the progress of teams and Business units in meeting their goals. • Agile Lifecycle Management tool expertise. Preferably with JIRA / Rally / AzureDevOps software. • Either possesses a background working directly in a technology role or can demonstrate the ability to understand the procedures and challenges of a variety of technology functions involved in the product development life cycle. • Flexible and resilient and willingness to take initiative to create approaches to complex problems. • Strong collaborative problem solver. • Exposure to XP engineering practices such as TDD, BDD, CI/ CD, Automation etc is a plus • Experience in tracking Agile metrics and also project metrics. • Ability to perform RCA and advise the project team on best measures • String knowledge on QAG process and respective metrics • Flexibly respond to shifting business needs and priorities. Certifications( At least One) • Scrum master • Safe Agilist • Project Management • Test Management Certifications(At least One) • SFDC Admin
C3: =_xlfn.CONCAT(A3,"_",B3) -> _
